{
  "db_rest": {
    "@generator": "zend",
    "@version": "1.0",
    "fetchArtistYear": {
      "shows": {
        "key_0": {
          "name": "Grateful Dead",
          "artist_key": "2",
          "shows_key": "830",
          "showdate": "02/09/73",
          "venue": "Roscoe Maples Pavilion, Stanford",
          "city": "Palo Alto",
          "state": "CA",
          "set1": [
            "Promised Land",
            "Row Jimmy",
            "Black Throated Wind",
            "Deal",
            "Me & My Uncle",
            "Sugaree",
            "Looks Like Rain",
            "Loose Lucy",
            "Mexicali Blues",
            "Brown Eyed Women",
            "El Paso",
            "Here Comes Sunshine",
            "Playin' In The Band"
          ],
          "set2": [
            "Promised Land",
            "Row Jimmy",
            "Black Throated Wind",
            "Deal",
            "Me & My Uncle",
            "Sugaree",
            "Looks Like Rain",
            "Loose Lucy",
            "Mexicali Blues",
            "Brown Eyed Women",
            "El Paso",
            "Here Comes Sunshine",
            "Playin' In The Band"
          ],
          "set3": "",
          "comment": "First Performances of: Row Jimmy, Loose Lucy, H.C.Sunshine, T.L.E.O., Eyes of the World, China Doll, Wave That Flag; \"Beer Barrel Polka\" tuning before \"Mexicali\".",
          "lastupdate": "2008-03-23 13:56:16",
          "showyear": "1973",
          "showsuserid": "mgoldey"
        },
        "key_1": {
          "name": "Grateful Dead",
          "artist_key": "2",
          "shows_key": "831",
          "showdate": "02/15/73",
          "venue": "Dane County Coliseum",
          "city": "Madison",
          "state": "WI",
          "set1": [
            "Loose Lucy",
            "Beat It On Down The Line",
            "Brown Eyed Women",
            "Mexicali Blues",
            "Tennessee Jed",
            "Looks Like Rain",
            "Box Of Rain",
            "Row Jimmy",
            "Jack Straw",
            "China Cat Sunflower-> I Know You Rider",
            "Me & My Uncle",
            "Bertha",
            "Playin' In The Band",
            "Casey Jones"
          ],
          "set2": [
            "Loose Lucy",
            "Beat It On Down The Line",
            "Brown Eyed Women",
            "Mexicali Blues",
            "Tennessee Jed",
            "Looks Like Rain",
            "Box Of Rain",
            "Row Jimmy",
            "Jack Straw",
            "China Cat Sunflower-> I Know You Rider",
            "Me & My Uncle",
            "Bertha",
            "Playin' In The Band",
            "Casey Jones"
          ],
          "set3": "",
          "comment": "",
          "lastupdate": "2001-03-01 00:00:00",
          "showyear": "1973",
          "showsuserid": "hamilton"
        },
        "key_2": {
          "name": "Grateful Dead",
          "artist_key": "2",
          "shows_key": "832",
          "showdate": "02/17/73",
          "venue": "St. Paul Auditorium",
          "city": "St. Paul",
          "state": "MN",
          "set1": [
            "Promised Land",
            "He's Gone",
            "Looks Like Rain",
            "Box Of Rain",
            "Wave That Flag",
            "Mexicali Blues",
            "Bird Song",
            "Beat It On Down The Line",
            "Loose Lucy",
            "Me And Bobby McGee",
            "Stella Blue",
            "El Paso",
            "They Love Each Other",
            "Playin' In The Band"
          ],
          "set2": [
            "Promised Land",
            "He's Gone",
            "Looks Like Rain",
            "Box Of Rain",
            "Wave That Flag",
            "Mexicali Blues",
            "Bird Song",
            "Beat It On Down The Line",
            "Loose Lucy",
            "Me And Bobby McGee",
            "Stella Blue",
            "El Paso",
            "They Love Each Other",
            "Playin' In The Band"
          ],
          "set3": "",
          "comment": "\"Beer Barrel Polka\" tuning before \"BIOTDL\"",
          "lastupdate": "2001-08-29 00:00:00",
          "showyear": "1973",
          "showsuserid": "system"
        },
        "key_3": {
          "name": "Grateful Dead",
          "artist_key": "2",
          "shows_key": "833",
          "showdate": "02/19/73",
          "venue": "International Amphitheatre",
          "city": "Chicago",
          "state": "IL",
          "set1": [
            "Promised Land",
            "Box Of Rain",
            "Brown Eyed Women",
            "El Paso"
          ],
          "set2": [
            "Promised Land",
            "Box Of Rain",
            "Brown Eyed Women",
            "El Paso"
          ],
          "set3": "",
          "comment": "setlist courtesy deadlists.com, citing Deadbase for set 1 info, vault for set 2 info.",
          "lastupdate": "2002-09-01 00:00:00",
          "showyear": "1973",
          "showsuserid": "hamilton"
        },
        "key_4": {
          "name": "Grateful Dead",
          "artist_key": "2",
          "shows_key": "834",
          "showdate": "02/21/73",
          "venue": "Assembly Hall, University Of Illinois",
          "city": "Champaign",
          "state": "IL",
          "set1": [
            "Wave That Flag",
            "Me & My Uncle",
            "Brown Eyed Women",
            "Beat It On Down The Line",
            "Loser",
            "Looks Like Rain",
            "Row Jimmy",
            "You Ain't Woman Enough",
            "Box Of Rain",
            "Mexicali Blues",
            "Sugaree",
            "Around & Around"
          ],
          "set2": [
            "Wave That Flag",
            "Me & My Uncle",
            "Brown Eyed Women",
            "Beat It On Down The Line",
            "Loser",
            "Looks Like Rain",
            "Row Jimmy",
            "You Ain't Woman Enough",
            "Box Of Rain",
            "Mexicali Blues",
            "Sugaree",
            "Around & Around"
          ],
          "set3": "",
          "comment": "",
          "lastupdate": "2010-06-21 11:23:01",
          "showyear": "1973",
          "showsuserid": "MusicNevStopped"
        },
        "key_5": {
          "name": "Grateful Dead",
          "artist_key": "2",
          "shows_key": "835",
          "showdate": "02/22/73",
          "venue": "Assembly Hall, University Of Illinois",
          "city": "Champaign",
          "state": "IL",
          "set1": [
            "Promised Land",
            "They Love Each Other",
            "El Paso",
            "Bird Song",
            "Mexicali Blues",
            "Deal",
            "Looks Like Rain",
            "Tennessee Jed",
            "Box Of Rain",
            "Playing In The Band"
          ],
          "set2": [
            "Promised Land",
            "They Love Each Other",
            "El Paso",
            "Bird Song",
            "Mexicali Blues",
            "Deal",
            "Looks Like Rain",
            "Tennessee Jed",
            "Box Of Rain",
            "Playing In The Band"
          ],
          "set3": "",
          "comment": "",
          "lastupdate": "2010-06-21 11:22:50",
          "showyear": "1973",
          "showsuserid": "MusicNevStopped"
        },
        "key_6": {
          "name": "Grateful Dead",
          "artist_key": "2",
          "shows_key": "836",
          "showdate": "02/24/73",
          "venue": "UI Field House, University Of Iowa",
          "city": "Iowa City",
          "state": "IA",
          "set1": [
            "Bertha",
            "Mexicali Blues",
            "Brown Eyed Women",
            "Looks Like Rain",
            "Loose Lucy",
            "Beat It On Down The Line",
            "China Cat Sunflower-> I Know You Rider",
            "Jack Straw",
            "Here Comes Sunshine",
            "El Paso",
            "Box Of Rain",
            "Tennessee Jed",
            "Playin' In The Band"
          ],
          "set2": [
            "Bertha",
            "Mexicali Blues",
            "Brown Eyed Women",
            "Looks Like Rain",
            "Loose Lucy",
            "Beat It On Down The Line",
            "China Cat Sunflower-> I Know You Rider",
            "Jack Straw",
            "Here Comes Sunshine",
            "El Paso",
            "Box Of Rain",
            "Tennessee Jed",
            "Playin' In The Band"
          ],
          "set3": "",
          "comment": "",
          "lastupdate": "2013-10-13 18:47:01",
          "showyear": "1973",
          "showsuserid": "BeLikeMike"
        },
        "key_7": {
          "name": "Grateful Dead",
          "artist_key": "2",
          "shows_key": "837",
          "showdate": "02/26/73",
          "venue": "Pershing Municipal Auditorium",
          "city": "Lincoln",
          "state": "NE",
          "set1": [
            "Promised Land",
            "Deal",
            "Mexicali Blues",
            "Loser",
            "Jack Straw",
            "Don't Ease Me In",
            "Box Of Rain",
            "China Cat Sunflower-> I Know You Rider",
            "Looks Like Rain",
            "Loose Lucy",
            "Beat It On Down The Line",
            "Row Jimmy",
            "El Paso",
            "Big Railroad Blues",
            "Playin' In The Band"
          ],
          "set2": [
            "Promised Land",
            "Deal",
            "Mexicali Blues",
            "Loser",
            "Jack Straw",
            "Don't Ease Me In",
            "Box Of Rain",
            "China Cat Sunflower-> I Know You Rider",
            "Looks Like Rain",
            "Loose Lucy",
            "Beat It On Down The Line",
            "Row Jimmy",
            "El Paso",
            "Big Railroad Blues",
            "Playin' In The Band"
          ],
          "set3": "",
          "comment": "This show is featured on Dick's Picks 28.",
          "lastupdate": "2003-08-19 00:00:00",
          "showyear": "1973",
          "showsuserid": "hamilton"
        },
        "key_8": {
          "name": "Grateful Dead",
          "artist_key": "2",
          "shows_key": "838",
          "showdate": "02/28/73",
          "venue": "Salt Palace",
          "city": "Salt Lake City",
          "state": "UT",
          "set1": [
            "Cold Rain & Snow",
            "Beat It On Down The Line",
            "They Love Each Other",
            "Mexicali Blues",
            "Sugaree",
            "Box Of Rain",
            "El Paso",
            "He's Gone",
            "Jack Straw"
          ],
          "set2": [
            "Cold Rain & Snow",
            "Beat It On Down The Line",
            "They Love Each Other",
            "Mexicali Blues",
            "Sugaree",
            "Box Of Rain",
            "El Paso",
            "He's Gone",
            "Jack Straw"
          ],
          "set3": "",
          "comment": "",
          "lastupdate": "1996-01-07 00:00:00",
          "showyear": "1973",
          "showsuserid": "system"
        },
        "key_9": {
          "name": "Grateful Dead",
          "artist_key": "2",
          "shows_key": "839",
          "showdate": "03/15/73",
          "venue": "Nassau Coliseum",
          "city": "Uniondale",
          "state": "NY",
          "set1": [
            "Promised Land",
            "Mississippi Half Step",
            "Mexicali Blues",
            "They Love Each Other",
            "Looks Like Rain",
            "Deal",
            "Beat It On Down The Line",
            "Box Of Rain",
            "Row Jimmy",
            "Me & My Uncle",
            "Tennessee Jed",
            "El Paso",
            "Here Comes Sunshine",
            "Playin' In The Band"
          ],
          "set2": [
            "Promised Land",
            "Mississippi Half Step",
            "Mexicali Blues",
            "They Love Each Other",
            "Looks Like Rain",
            "Deal",
            "Beat It On Down The Line",
            "Box Of Rain",
            "Row Jimmy",
            "Me & My Uncle",
            "Tennessee Jed",
            "El Paso",
            "Here Comes Sunshine",
            "Playin' In The Band"
          ],
          "set3": "",
          "comment": "\"A Swell Dance Concert\" - Other artist(s): GD; Sons of Champlin",
          "lastupdate": "1996-01-07 00:00:00",
          "showyear": "1973",
          "showsuserid": "system"
        },
        "key_10": {
          "name": "Grateful Dead",
          "artist_key": "2",
          "shows_key": "840",
          "showdate": "03/16/73",
          "venue": "Nassau Veterans Memorial Coliseum",
          "city": "Uniondale",
          "state": "NY",
          "set1": [
            "China Cat Sunflower-> I Know You Rider",
            "Jack Straw",
            "Wave That Flag",
            "Looks Like Rain",
            "Ramble On Rose",
            "Box Of Rain",
            "Beat It On Down The Line",
            "They Love Each Other",
            "El Paso",
            "Row Jimmy",
            "Mexicali Blues",
            "Bird Song",
            "Playin' In The Band"
          ],
          "set2": [
            "China Cat Sunflower-> I Know You Rider",
            "Jack Straw",
            "Wave That Flag",
            "Looks Like Rain",
            "Ramble On Rose",
            "Box Of Rain",
            "Beat It On Down The Line",
            "They Love Each Other",
            "El Paso",
            "Row Jimmy",
            "Mexicali Blues",
            "Bird Song",
            "Playin' In The Band"
          ],
          "set3": "",
          "comment": "\"A Swell Dance Concert\" - Artist(s) on bill: GD; Sons of Champlin  (That's how it was billed; in fact, SOC didn't play due to the death of the lead singer's father, so NRPS opened instead.)",
          "lastupdate": "2010-06-21 11:48:07",
          "showyear": "1973",
          "showsuserid": "MusicNevStopped"
        },
        "key_11": {
          "name": "Grateful Dead",
          "artist_key": "2",
          "shows_key": "841",
          "showdate": "03/19/73",
          "venue": "Nassau Veterans Memorial Coliseum",
          "city": "Uniondale",
          "state": "NY",
          "set1": [
            "Promised Land",
            "He's Gone",
            "Mexicali Blues",
            "They Love Each Other",
            "Looks Like Rain",
            "Wave That Flag",
            "Box Of Rain",
            "The Race is On",
            "Row Jimmy",
            "El Paso",
            "China Cat Sunflower-> I Know You Rider",
            "Around & Around",
            "Tennessee Jed",
            "Playin' In The Band"
          ],
          "set2": [
            "Promised Land",
            "He's Gone",
            "Mexicali Blues",
            "They Love Each Other",
            "Looks Like Rain",
            "Wave That Flag",
            "Box Of Rain",
            "The Race is On",
            "Row Jimmy",
            "El Paso",
            "China Cat Sunflower-> I Know You Rider",
            "Around & Around",
            "Tennessee Jed",
            "Playin' In The Band"
          ],
          "set3": "",
          "comment": "",
          "lastupdate": "2010-06-21 11:47:36",
          "showyear": "1973",
          "showsuserid": "MusicNevStopped"
        },
        "key_12": {
          "name": "Grateful Dead",
          "artist_key": "2",
          "shows_key": "842",
          "showdate": "03/21/73",
          "venue": "Utica Memorial Auditorium",
          "city": "Utica",
          "state": "NY",
          "set1": [
            "Bertha",
            "Me & My Uncle",
            "Wave That Flag",
            "Looks Like Rain",
            "Tennessee Jed",
            "Box Of Rain",
            "You Ain't Woman Enough",
            "Jack Straw",
            "Row Jimmy",
            "Beat It On Down The Line",
            "Here Comes Sunshine",
            "The Race is On",
            "Loser",
            "El Paso",
            "China Cat Sunflower-> I Know You Rider",
            "Playin' In The Band"
          ],
          "set2": [
            "Bertha",
            "Me & My Uncle",
            "Wave That Flag",
            "Looks Like Rain",
            "Tennessee Jed",
            "Box Of Rain",
            "You Ain't Woman Enough",
            "Jack Straw",
            "Row Jimmy",
            "Beat It On Down The Line",
            "Here Comes Sunshine",
            "The Race is On",
            "Loser",
            "El Paso",
            "China Cat Sunflower-> I Know You Rider",
            "Playin' In The Band"
          ],
          "set3": "",
          "comment": "",
          "lastupdate": "1996-01-07 00:00:00",
          "showyear": "1973",
          "showsuserid": "stark1"
        },
        "key_13": {
          "name": "Grateful Dead",
          "artist_key": "2",
          "shows_key": "843",
          "showdate": "03/22/73",
          "venue": "Utica Memorial Auditorium",
          "city": "Utica",
          "state": "NY",
          "set1": [
            "Promised Land",
            "Sugaree",
            "Mexicali Blues",
            "They Love Each Other",
            "Looks Like Rain",
            "Deal",
            "Beat It On Down The Line",
            "Bird Song",
            "Jack Straw",
            "Box Of Rain",
            "You Ain't Woman Enough",
            "The Race is On",
            "Row Jimmy",
            "El Paso",
            "China Cat Sunflower-&gt; I Know You Rider",
            "Playing In The Band"
          ],
          "set2": [
            "Promised Land",
            "Sugaree",
            "Mexicali Blues",
            "They Love Each Other",
            "Looks Like Rain",
            "Deal",
            "Beat It On Down The Line",
            "Bird Song",
            "Jack Straw",
            "Box Of Rain",
            "You Ain't Woman Enough",
            "The Race is On",
            "Row Jimmy",
            "El Paso",
            "China Cat Sunflower-&gt; I Know You Rider",
            "Playing In The Band"
          ],
          "set3": "",
          "comment": "",
          "lastupdate": "2012-09-15 18:29:07",
          "showyear": "1973",
          "showsuserid": "aikox2"
        },
        "key_14": {
          "name": "Grateful Dead",
          "artist_key": "2",
          "shows_key": "844",
          "showdate": "03/24/73",
          "venue": "The Spectrum",
          "city": "Philadelphia",
          "state": "PA",
          "set1": [
            "Bertha\nBeat It On Down The Line\nDon't Ease Me In\nThe Race Is On\nCumberland Blues\nBox Of Rain\nRow Jimmy\nJack Straw\nThey Love Each Other\nMexicali Blues\nTennessee Jed\nLooks Like Rain\nWave That Flag\nEl Paso\nHere Comes Sunshine\nMe And Bobby McGee\nLoser\nPlayin' In The Band"
          ],
          "set2": [
            "Bertha\nBeat It On Down The Line\nDon't Ease Me In\nThe Race Is On\nCumberland Blues\nBox Of Rain\nRow Jimmy\nJack Straw\nThey Love Each Other\nMexicali Blues\nTennessee Jed\nLooks Like Rain\nWave That Flag\nEl Paso\nHere Comes Sunshine\nMe And Bobby McGee\nLoser\nPlayin' In The Band"
          ],
          "set3": "",
          "comment": "",
          "lastupdate": "2012-10-27 01:20:45",
          "showyear": "1973",
          "showsuserid": "snockaholic"
        },
        "key_15": {
          "name": "Grateful Dead",
          "artist_key": "2",
          "shows_key": "845",
          "showdate": "03/26/73",
          "venue": "Baltimore Civic Center",
          "city": "Baltimore",
          "state": "MD",
          "set1": [
            "Promised Land",
            "Mississippi Half Step",
            "The Race is On",
            "Wave That Flag",
            "Jack Straw",
            "Sugaree",
            "Mexicali Blues",
            "Box Of Rain",
            "Row Jimmy",
            "Beat It On Down The Line",
            "Brown Eyed Women",
            "El Paso",
            "China Cat Sunflower-> I Know You Rider",
            "Looks Like Rain",
            "Don't Ease Me In",
            "Playin' In The Band"
          ],
          "set2": [
            "Promised Land",
            "Mississippi Half Step",
            "The Race is On",
            "Wave That Flag",
            "Jack Straw",
            "Sugaree",
            "Mexicali Blues",
            "Box Of Rain",
            "Row Jimmy",
            "Beat It On Down The Line",
            "Brown Eyed Women",
            "El Paso",
            "China Cat Sunflower-> I Know You Rider",
            "Looks Like Rain",
            "Don't Ease Me In",
            "Playin' In The Band"
          ],
          "set3": "",
          "comment": "",
          "lastupdate": "1996-01-07 00:00:00",
          "showyear": "1973",
          "showsuserid": "system"
        },
        "key_16": {
          "name": "Grateful Dead",
          "artist_key": "2",
          "shows_key": "846",
          "showdate": "03/28/73",
          "venue": "Springfield Civic Center",
          "city": "Springfield",
          "state": "MA",
          "set1": [
            "Cumberland Blues",
            "Here Comes Sunshine",
            "Mexicali Blues",
            "Wave That Flag",
            "Beat It On Down The Line",
            "Loser",
            "Jack Straw",
            "Box Of Rain",
            "They Love Each Other",
            "El Paso",
            "Row Jimmy",
            "Around & Around",
            "Brown Eyed Women",
            "You Ain't Woman Enough",
            "Looks Like Rain",
            "China Cat Sunflower-> I Know You Rider"
          ],
          "set2": [
            "Cumberland Blues",
            "Here Comes Sunshine",
            "Mexicali Blues",
            "Wave That Flag",
            "Beat It On Down The Line",
            "Loser",
            "Jack Straw",
            "Box Of Rain",
            "They Love Each Other",
            "El Paso",
            "Row Jimmy",
            "Around & Around",
            "Brown Eyed Women",
            "You Ain't Woman Enough",
            "Looks Like Rain",
            "China Cat Sunflower-> I Know You Rider"
          ],
          "set3": "",
          "comment": "",
          "lastupdate": "1996-01-07 00:00:00",
          "showyear": "1973",
          "showsuserid": "system"
        },
        "key_17": {
          "name": "Grateful Dead",
          "artist_key": "2",
          "shows_key": "847",
          "showdate": "03/30/73",
          "venue": "Rochester Community War Memorial",
          "city": "Rochester",
          "state": "NY",
          "set1": [
            "Promised Land",
            "Deal",
            "Looks Like Rain",
            "They Love Each Other",
            "Mexicali Blues",
            "Box Of Rain",
            "Cumberland Blues",
            "Candyman",
            "Beat It On Down The Line",
            "Don't Ease Me In",
            "El Paso",
            "Row Jimmy",
            "The Race is On",
            "Bird Song",
            "Playin' In The Band"
          ],
          "set2": [
            "Promised Land",
            "Deal",
            "Looks Like Rain",
            "They Love Each Other",
            "Mexicali Blues",
            "Box Of Rain",
            "Cumberland Blues",
            "Candyman",
            "Beat It On Down The Line",
            "Don't Ease Me In",
            "El Paso",
            "Row Jimmy",
            "The Race is On",
            "Bird Song",
            "Playin' In The Band"
          ],
          "set3": "",
          "comment": "",
          "lastupdate": "1996-01-07 00:00:00",
          "showyear": "1973",
          "showsuserid": "system"
        },
        "key_18": {
          "name": "Grateful Dead",
          "artist_key": "2",
          "shows_key": "848",
          "showdate": "03/31/73",
          "venue": "Buffalo Memorial Auditorium",
          "city": "Buffalo",
          "state": "NY",
          "set1": [
            "Mississippi Half Step",
            "The Race is On",
            "Sugaree",
            "Mexicali Blues",
            "Box Of Rain",
            "Tennessee Jed",
            "Jack Straw",
            "Big Railroad Blues",
            "El Paso",
            "Row Jimmy",
            "Looks Like Rain",
            "They Love Each Other",
            "Playin' In The Band"
          ],
          "set2": [
            "Mississippi Half Step",
            "The Race is On",
            "Sugaree",
            "Mexicali Blues",
            "Box Of Rain",
            "Tennessee Jed",
            "Jack Straw",
            "Big Railroad Blues",
            "El Paso",
            "Row Jimmy",
            "Looks Like Rain",
            "They Love Each Other",
            "Playin' In The Band"
          ],
          "set3": "",
          "comment": "",
          "lastupdate": "1996-01-07 00:00:00",
          "showyear": "1973",
          "showsuserid": "hamilton"
        },
        "key_19": {
          "name": "Grateful Dead",
          "artist_key": "2",
          "shows_key": "849",
          "showdate": "04/02/73",
          "venue": "Boston Garden",
          "city": "Boston",
          "state": "MA",
          "set1": [
            "Promised Land",
            "Deal",
            "Mexicali Blues",
            "Brown Eyed Women",
            "Beat It On Down The Line",
            "Row Jimmy",
            "Looks Like Rain",
            "Wave That Flag",
            "Box Of Rain",
            "Big River",
            "China Cat Sunflower-> I Know You Rider",
            "You Ain't Woman Enough",
            "Jack Straw",
            "Don't Ease Me In",
            "Playin' In The Band"
          ],
          "set2": [
            "Promised Land",
            "Deal",
            "Mexicali Blues",
            "Brown Eyed Women",
            "Beat It On Down The Line",
            "Row Jimmy",
            "Looks Like Rain",
            "Wave That Flag",
            "Box Of Rain",
            "Big River",
            "China Cat Sunflower-> I Know You Rider",
            "You Ain't Woman Enough",
            "Jack Straw",
            "Don't Ease Me In",
            "Playin' In The Band"
          ],
          "set3": "",
          "comment": "",
          "lastupdate": "1996-01-07 00:00:00",
          "showyear": "1973",
          "showsuserid": "greenone"
        },
        "key_20": {
          "name": "Grateful Dead",
          "artist_key": "2",
          "shows_key": "850",
          "showdate": "05/13/73",
          "venue": "Iowa State Fairgrounds",
          "city": "Des Moines",
          "state": "IA",
          "set1": [
            "Promised Land",
            "Deal",
            "Mexicali Blues",
            "They Love Each Other",
            "Box Of Rain",
            "Loser",
            "China Cat Sunflower-> I Know You Rider",
            "Beat It On Down The Line",
            "El Paso",
            "Row Jimmy",
            "Me & My Uncle",
            "Don't Ease Me In-> Around & Around"
          ],
          "set2": [
            "Promised Land",
            "Deal",
            "Mexicali Blues",
            "They Love Each Other",
            "Box Of Rain",
            "Loser",
            "China Cat Sunflower-> I Know You Rider",
            "Beat It On Down The Line",
            "El Paso",
            "Row Jimmy",
            "Me & My Uncle",
            "Don't Ease Me In-> Around & Around"
          ],
          "set3": [
            "Promised Land",
            "Deal",
            "Mexicali Blues",
            "They Love Each Other",
            "Box Of Rain",
            "Loser",
            "China Cat Sunflower-> I Know You Rider",
            "Beat It On Down The Line",
            "El Paso",
            "Row Jimmy",
            "Me & My Uncle",
            "Don't Ease Me In-> Around & Around"
          ],
          "comment": "",
          "lastupdate": "1996-01-07 00:00:00",
          "showyear": "1973",
          "showsuserid": "Wharfrat73"
        },
        "key_21": {
          "name": "Grateful Dead",
          "artist_key": "2",
          "shows_key": "851",
          "showdate": "05/20/73",
          "venue": "Stadium, U.C Santa Barbara",
          "city": "Santa Barbara",
          "state": "CA",
          "set1": [
            "Bertha",
            "Me & My Uncle",
            "Box Of Rain",
            "Deal",
            "Looks Like Rain",
            "Tennessee Jed",
            "The Race is On",
            "China Cat Sunflower-> I Know You Rider",
            "Beat It On Down The Line",
            "They Love Each Other",
            "Playin' In The Band"
          ],
          "set2": [
            "Bertha",
            "Me & My Uncle",
            "Box Of Rain",
            "Deal",
            "Looks Like Rain",
            "Tennessee Jed",
            "The Race is On",
            "China Cat Sunflower-> I Know You Rider",
            "Beat It On Down The Line",
            "They Love Each Other",
            "Playin' In The Band"
          ],
          "set3": [
            "Bertha",
            "Me & My Uncle",
            "Box Of Rain",
            "Deal",
            "Looks Like Rain",
            "Tennessee Jed",
            "The Race is On",
            "China Cat Sunflower-> I Know You Rider",
            "Beat It On Down The Line",
            "They Love Each Other",
            "Playin' In The Band"
          ],
          "comment": "Afternoon concert - Other artist(s): NRPS",
          "lastupdate": "1996-01-07 00:00:00",
          "showyear": "1973",
          "showsuserid": "system"
        },
        "key_22": {
          "name": "Grateful Dead",
          "artist_key": "2",
          "shows_key": "852",
          "showdate": "05/26/73",
          "venue": "Kezar Stadium",
          "city": "San Francisco",
          "state": "CA",
          "set1": [
            "Promised Land",
            "Deal",
            "Jack Straw",
            "Tennessee Jed",
            "The Race is On",
            "Sugaree",
            "Mexicali Blues",
            "Row Jimmy",
            "Looks Like Rain",
            "They Love Each Other",
            "Playin' In The Band"
          ],
          "set2": [
            "Promised Land",
            "Deal",
            "Jack Straw",
            "Tennessee Jed",
            "The Race is On",
            "Sugaree",
            "Mexicali Blues",
            "Row Jimmy",
            "Looks Like Rain",
            "They Love Each Other",
            "Playin' In The Band"
          ],
          "set3": [
            "Promised Land",
            "Deal",
            "Jack Straw",
            "Tennessee Jed",
            "The Race is On",
            "Sugaree",
            "Mexicali Blues",
            "Row Jimmy",
            "Looks Like Rain",
            "They Love Each Other",
            "Playin' In The Band"
          ],
          "comment": "Afternoon concert; Other artist(s): NRPS, Waylon Jennings",
          "lastupdate": "2010-04-18 12:12:33",
          "showyear": "1973",
          "showsuserid": "harmon"
        },
        "key_23": {
          "name": "Grateful Dead",
          "artist_key": "2",
          "shows_key": "853",
          "showdate": "06/09/73",
          "venue": "Robert F. Kennedy Stadium",
          "city": "Washington",
          "state": "DC",
          "set1": [
            "Promised Land",
            "Deal",
            "Looks Like Rain",
            "They Love Each Other",
            "Jack Straw",
            "Loose Lucy",
            "Mexicali Blues",
            "Row Jimmy",
            "El Paso",
            "Box Of Rain",
            "Sugaree",
            "Beat It On Down The Line",
            "Tennessee Jed"
          ],
          "set2": [
            "Promised Land",
            "Deal",
            "Looks Like Rain",
            "They Love Each Other",
            "Jack Straw",
            "Loose Lucy",
            "Mexicali Blues",
            "Row Jimmy",
            "El Paso",
            "Box Of Rain",
            "Sugaree",
            "Beat It On Down The Line",
            "Tennessee Jed"
          ],
          "set3": "",
          "comment": "Sound check: China Cat->I Know You Rider. Do",
          "lastupdate": "2014-06-12 12:09:53",
          "showyear": "1973",
          "showsuserid": "duggy"
        },
        "key_24": {
          "name": "Grateful Dead",
          "artist_key": "2",
          "shows_key": "854",
          "showdate": "06/10/73",
          "venue": "Robert F. Kennedy Stadium",
          "city": "Washington",
          "state": "DC",
          "set1": [
            "Morning Dew",
            "Beat It On Down The Line",
            "Ramble On Rose",
            "Jack Straw",
            "Wave That Flag#",
            "Looks Like Rain",
            "Box Of Rain",
            "They Love Each Other",
            "The Race Is On",
            "Row Jimmy",
            "El Paso",
            "Bird Song",
            "Playin' In The Band"
          ],
          "set2": [
            "Morning Dew",
            "Beat It On Down The Line",
            "Ramble On Rose",
            "Jack Straw",
            "Wave That Flag#",
            "Looks Like Rain",
            "Box Of Rain",
            "They Love Each Other",
            "The Race Is On",
            "Row Jimmy",
            "El Paso",
            "Bird Song",
            "Playin' In The Band"
          ],
          "set3": [
            "Morning Dew",
            "Beat It On Down The Line",
            "Ramble On Rose",
            "Jack Straw",
            "Wave That Flag#",
            "Looks Like Rain",
            "Box Of Rain",
            "They Love Each Other",
            "The Race Is On",
            "Row Jimmy",
            "El Paso",
            "Bird Song",
            "Playin' In The Band"
          ],
          "comment": "Wet Willie And The Allman Brothers Band Opened\n\n* - w/ Butch Trucks, Dickey Betts And Merl Saunders\n^ - First Time Played\n# - Last Time Played",
          "lastupdate": "2010-08-07 19:39:28",
          "showyear": "1973",
          "showsuserid": "Oldneumanntapr"
        },
        "key_25": {
          "name": "Grateful Dead",
          "artist_key": "2",
          "shows_key": "855",
          "showdate": "06/22/73",
          "venue": "P.N.E. Coliseum",
          "city": "Vancouver",
          "state": "BC",
          "set1": [
            "Bertha",
            "Beat It On Down The Line",
            "Deal",
            "Mexicali Blues",
            "Box Of Rain",
            "Bird Song",
            "The Race is On",
            "Sugaree",
            "Looks Like Rain",
            "Row Jimmy",
            "Jack Straw",
            "China Cat Sunflower-> I Know You Rider",
            "Big River",
            "Tennessee Jed",
            "Playin' In The Band"
          ],
          "set2": [
            "Bertha",
            "Beat It On Down The Line",
            "Deal",
            "Mexicali Blues",
            "Box Of Rain",
            "Bird Song",
            "The Race is On",
            "Sugaree",
            "Looks Like Rain",
            "Row Jimmy",
            "Jack Straw",
            "China Cat Sunflower-> I Know You Rider",
            "Big River",
            "Tennessee Jed",
            "Playin' In The Band"
          ],
          "set3": "",
          "comment": "",
          "lastupdate": "2001-11-05 00:00:00",
          "showyear": "1973",
          "showsuserid": "hamilton"
        },
        "key_26": {
          "name": "Grateful Dead",
          "artist_key": "2",
          "shows_key": "856",
          "showdate": "06/24/73",
          "venue": "Portland Memorial Coliseum",
          "city": "Portland",
          "state": "OR",
          "set1": [
            "Promised Land\nLoser\nMexicali Blues\nThey Love Each Other\nLooks Like Rain\nBox Of Rain\nBig Railroad Blues\nJack Straw\nSugaree\nThe Race Is On\nRow Jimmy\nBeat It On Down The Line\nChina Cat Sunflower -&gt;\nI Know You Rider\nAround and Around"
          ],
          "set2": [
            "Promised Land\nLoser\nMexicali Blues\nThey Love Each Other\nLooks Like Rain\nBox Of Rain\nBig Railroad Blues\nJack Straw\nSugaree\nThe Race Is On\nRow Jimmy\nBeat It On Down The Line\nChina Cat Sunflower -&gt;\nI Know You Rider\nAround and Around"
          ],
          "set3": "",
          "comment": "",
          "lastupdate": "2009-07-01 21:20:48",
          "showyear": "1973",
          "showsuserid": "ziko"
        },
        "key_27": {
          "name": "Grateful Dead",
          "artist_key": "2",
          "shows_key": "857",
          "showdate": "06/26/73",
          "venue": "Seattle Center Arena",
          "city": "Seattle",
          "state": "WA",
          "set1": [
            "Casey Jones-> Greatest Story Ever Told",
            "Brown Eyed Women",
            "Jack Straw",
            "Box Of Rain",
            "Deal",
            "Mexicali Blues",
            "You Ain't Woman Enough",
            "Row Jimmy",
            "The Race is On",
            "Cumberland Blues",
            "China Cat Sunflower-> I Know You Rider",
            "Beat It On Down The Line",
            "Loser",
            "Playin' In The Band"
          ],
          "set2": [
            "Casey Jones-> Greatest Story Ever Told",
            "Brown Eyed Women",
            "Jack Straw",
            "Box Of Rain",
            "Deal",
            "Mexicali Blues",
            "You Ain't Woman Enough",
            "Row Jimmy",
            "The Race is On",
            "Cumberland Blues",
            "China Cat Sunflower-> I Know You Rider",
            "Beat It On Down The Line",
            "Loser",
            "Playin' In The Band"
          ],
          "set3": "",
          "comment": "",
          "lastupdate": "2002-11-27 00:00:00",
          "showyear": "1973",
          "showsuserid": "system"
        },
        "key_28": {
          "name": "Grateful Dead",
          "artist_key": "2",
          "shows_key": "858",
          "showdate": "06/29/73",
          "venue": "Universal Amphitheatre",
          "city": "Universal City",
          "state": "CA",
          "set1": [
            "Bertha",
            "Me & My Uncle",
            "Sugaree",
            "The Race is On",
            "Looks Like Rain",
            "Don't Ease Me In",
            "Big River",
            "Row Jimmy",
            "Loose Lucy",
            "China Cat Sunflower-> I Know You Rider",
            "Jack Straw",
            "Deal",
            "Playin' In The Band"
          ],
          "set2": [
            "Bertha",
            "Me & My Uncle",
            "Sugaree",
            "The Race is On",
            "Looks Like Rain",
            "Don't Ease Me In",
            "Big River",
            "Row Jimmy",
            "Loose Lucy",
            "China Cat Sunflower-> I Know You Rider",
            "Jack Straw",
            "Deal",
            "Playin' In The Band"
          ],
          "set3": "",
          "comment": "",
          "lastupdate": "1996-01-07 00:00:00",
          "showyear": "1973",
          "showsuserid": "system"
        },
        "key_29": {
          "name": "Grateful Dead",
          "artist_key": "2",
          "shows_key": "859",
          "showdate": "06/30/73",
          "venue": "Universal Amphitheatre",
          "city": "Universal City",
          "state": "CA",
          "set1": [
            "Promised Land",
            "They Love Each Other",
            "Mexicali Blues",
            "Tennessee Jed",
            "Looks Like Rain",
            "Bird Song",
            "Cumberland Blues",
            "Row Jimmy",
            "Jack Straw",
            "Deal",
            "Beat It On Down The Line",
            "Black Peter",
            "Playin' In The Band"
          ],
          "set2": [
            "Promised Land",
            "They Love Each Other",
            "Mexicali Blues",
            "Tennessee Jed",
            "Looks Like Rain",
            "Bird Song",
            "Cumberland Blues",
            "Row Jimmy",
            "Jack Straw",
            "Deal",
            "Beat It On Down The Line",
            "Black Peter",
            "Playin' In The Band"
          ],
          "set3": "",
          "comment": "Total solar eclipse not total at show",
          "lastupdate": "1996-01-07 00:00:00",
          "showyear": "1973",
          "showsuserid": "system"
        },
        "key_30": {
          "name": "Grateful Dead",
          "artist_key": "2",
          "shows_key": "860",
          "showdate": "07/01/73",
          "venue": "Universal Amphitheatre",
          "city": "Universal City",
          "state": "CA",
          "set1": [
            "Mississippi Half Step",
            "Me & My Uncle",
            "Sugaree",
            "The Race is On",
            "Brown Eyed Women",
            "Looks Like Rain",
            "Don't Ease Me In",
            "Big River",
            "China Cat Sunflower-> I Know You Rider",
            "Around & Around"
          ],
          "set2": [
            "Mississippi Half Step",
            "Me & My Uncle",
            "Sugaree",
            "The Race is On",
            "Brown Eyed Women",
            "Looks Like Rain",
            "Don't Ease Me In",
            "Big River",
            "China Cat Sunflower-> I Know You Rider",
            "Around & Around"
          ],
          "set3": "",
          "comment": "",
          "lastupdate": "1996-01-07 00:00:00",
          "showyear": "1973",
          "showsuserid": "system"
        },
        "key_31": {
          "name": "Grateful Dead",
          "artist_key": "2",
          "shows_key": "861",
          "showdate": "07/27/73",
          "venue": "Grand Prix Racecourse",
          "city": "Watkins Glen",
          "state": "NY",
          "set1": [
            "Promised Land",
            "Sugaree",
            "Mexicali Blues",
            "Bird Song",
            "Big River",
            "Tennessee Jed"
          ],
          "set2": [
            "Promised Land",
            "Sugaree",
            "Mexicali Blues",
            "Bird Song",
            "Big River",
            "Tennessee Jed"
          ],
          "set3": "",
          "comment": "\"Merry-Go-Round Broke Down\" tuning after \"Tennessee jed \" Sound Check for 07-28-73",
          "lastupdate": "1996-01-07 00:00:00",
          "showyear": "1973",
          "showsuserid": "system"
        },
        "key_32": {
          "name": "Grateful Dead",
          "artist_key": "2",
          "shows_key": "862",
          "showdate": "07/28/73",
          "venue": "Grand Prix Racecourse",
          "city": "Watkins Glen",
          "state": "NY",
          "set1": [
            "Bertha",
            "Beat It On Down The Line",
            "Brown Eyed Women",
            "Mexicali Blues",
            "Box Of Rain",
            "Here Comes Sunshine",
            "Looks Like Rain",
            "Row Jimmy",
            "Jack Straw",
            "Deal",
            "Playin' In The Band"
          ],
          "set2": [
            "Bertha",
            "Beat It On Down The Line",
            "Brown Eyed Women",
            "Mexicali Blues",
            "Box Of Rain",
            "Here Comes Sunshine",
            "Looks Like Rain",
            "Row Jimmy",
            "Jack Straw",
            "Deal",
            "Playin' In The Band"
          ],
          "set3": [
            "Bertha",
            "Beat It On Down The Line",
            "Brown Eyed Women",
            "Mexicali Blues",
            "Box Of Rain",
            "Here Comes Sunshine",
            "Looks Like Rain",
            "Row Jimmy",
            "Jack Straw",
            "Deal",
            "Playin' In The Band"
          ],
          "comment": "*wi\\ the Allman Brothers and The Band",
          "lastupdate": "1996-01-07 00:00:00",
          "showyear": "1973",
          "showsuserid": "system"
        },
        "key_33": {
          "name": "Grateful Dead",
          "artist_key": "2",
          "shows_key": "863",
          "showdate": "07/31/73",
          "venue": "Roosevelt Stadium",
          "city": "Jersey City",
          "state": "NJ",
          "set1": [
            "Ramble On Rose",
            "Me & My Uncle",
            "Don't Ease Me In",
            "Beat It On Down The Line",
            "Brown Eyed Women",
            "Mexicali Blues",
            "Loser",
            "Jack Straw",
            "They Love Each Other",
            "Looks Like Rain",
            "Tennessee Jed",
            "El Paso",
            "China Cat Sunflower-> I Know You Rider",
            "Playin' In The Band"
          ],
          "set2": [
            "Ramble On Rose",
            "Me & My Uncle",
            "Don't Ease Me In",
            "Beat It On Down The Line",
            "Brown Eyed Women",
            "Mexicali Blues",
            "Loser",
            "Jack Straw",
            "They Love Each Other",
            "Looks Like Rain",
            "Tennessee Jed",
            "El Paso",
            "China Cat Sunflower-> I Know You Rider",
            "Playin' In The Band"
          ],
          "set3": "",
          "comment": "Other artist(s): The Band",
          "lastupdate": "1996-01-07 00:00:00",
          "showyear": "1973",
          "showsuserid": "system"
        },
        "key_34": {
          "name": "Grateful Dead",
          "artist_key": "2",
          "shows_key": "864",
          "showdate": "08/01/73",
          "venue": "Roosevelt Stadium",
          "city": "Jersey City",
          "state": "NJ",
          "set1": [
            "Promised Land",
            "Sugaree",
            "The Race is On",
            "You Ain't Woman Enough",
            "Bird Song",
            "Mexicali Blues",
            "They Love Each Other",
            "Jack Straw",
            "Stella Blue",
            "Big River",
            "Casey Jones"
          ],
          "set2": [
            "Promised Land",
            "Sugaree",
            "The Race is On",
            "You Ain't Woman Enough",
            "Bird Song",
            "Mexicali Blues",
            "They Love Each Other",
            "Jack Straw",
            "Stella Blue",
            "Big River",
            "Casey Jones"
          ],
          "set3": "",
          "comment": "Other artist(s): The Band",
          "lastupdate": "2001-06-04 00:00:00",
          "showyear": "1973",
          "showsuserid": "hamilton"
        },
        "key_35": {
          "name": "Grateful Dead",
          "artist_key": "2",
          "shows_key": "53161",
          "showdate": "08/??/73",
          "venue": "Record Plant",
          "city": "Sausalito",
          "state": "CA",
          "set1": [
            "Here Comes Sunshine\nHere Comes Sunshine Take 2\nLet Me Sing Your Blues Away\nLet It Grow\nRow Jimmy\nEyes of the World\nWRS Prelude-&gt; WRS Part 1\nWRS Prelude Take 2\nWRS Prelude-&gt; WRS Part 1 Take 3\nStella Blue\nStella Blue Take 2\nHere Comes Sunshine Take 3\nHere Comes Sunshine Take 4\nLet Me Sing Your Blues Away Take 2"
          ],
          "set2": "",
          "set3": "",
          "comment": "Wake of the Flood Outtakes; <a href=\"http://web.archive.org/web/*/http://www.bettyboards.deadhead.com/73-08-wake\">more info</a>",
          "lastupdate": "2010-06-21 11:30:14",
          "showyear": "1973",
          "showsuserid": "MusicNevStopped"
        },
        "key_36": {
          "name": "Grateful Dead",
          "artist_key": "2",
          "shows_key": "866",
          "showdate": "09/07/73",
          "venue": "Nassau Veterans Memorial Coliseum",
          "city": "Uniondale",
          "state": "NY",
          "set1": [
            "Promised Land",
            "Sugaree",
            "Mexicali Blues",
            "They Love Each Other",
            "Jack Straw",
            "Row Jimmy",
            "Looks Like Rain",
            "Deal",
            "El Paso",
            "Bird Song",
            "Playin' In The Band"
          ],
          "set2": [
            "Promised Land",
            "Sugaree",
            "Mexicali Blues",
            "They Love Each Other",
            "Jack Straw",
            "Row Jimmy",
            "Looks Like Rain",
            "Deal",
            "El Paso",
            "Bird Song",
            "Playin' In The Band"
          ],
          "set3": "",
          "comment": "",
          "lastupdate": "2010-06-21 11:47:50",
          "showyear": "1973",
          "showsuserid": "MusicNevStopped"
        },
        "key_37": {
          "name": "Grateful Dead",
          "artist_key": "2",
          "shows_key": "865",
          "showdate": "09/08/73",
          "venue": "Nassau Coliseum",
          "city": "Uniondale",
          "state": "NY",
          "set1": [
            "Bertha",
            "Me & My Uncle",
            "Sugaree",
            "Beat It On Down The Line",
            "Tennessee Jed",
            "Looks Like Rain",
            "Brown Eyed Women",
            "Jack Straw",
            "Row Jimmy Row",
            "Weather Report Suite Prelude-> Weather Report Suite Part 1-> Let It Grow",
            "Eyes Of The World-> China Doll"
          ],
          "set2": [
            "Bertha",
            "Me & My Uncle",
            "Sugaree",
            "Beat It On Down The Line",
            "Tennessee Jed",
            "Looks Like Rain",
            "Brown Eyed Women",
            "Jack Straw",
            "Row Jimmy Row",
            "Weather Report Suite Prelude-> Weather Report Suite Part 1-> Let It Grow",
            "Eyes Of The World-> China Doll"
          ],
          "set3": "",
          "comment": "",
          "lastupdate": "2002-03-01 00:00:00",
          "showyear": "1973",
          "showsuserid": "hamilton"
        },
        "key_38": {
          "name": "Grateful Dead",
          "artist_key": "2",
          "shows_key": "867",
          "showdate": "09/11/73",
          "venue": "William and Mary College Hall",
          "city": "Williamsburg",
          "state": "VA",
          "set1": [
            "Promised Land",
            "Sugaree",
            "The Race is On",
            "Loser",
            "Looks Like Rain",
            "Tennessee Jed",
            "Jack Straw",
            "China Cat Sunflower-> I Know You Rider",
            "El Paso",
            "Mississippi Half Step",
            "Playin' In The Band"
          ],
          "set2": [
            "Promised Land",
            "Sugaree",
            "The Race is On",
            "Loser",
            "Looks Like Rain",
            "Tennessee Jed",
            "Jack Straw",
            "China Cat Sunflower-> I Know You Rider",
            "El Paso",
            "Mississippi Half Step",
            "Playin' In The Band"
          ],
          "set3": "",
          "comment": "*with Martin Fiero and Joe Ellis on horns. Doug Sahm opened; First Let Me Sing",
          "lastupdate": "2005-02-21 00:00:00",
          "showyear": "1973",
          "showsuserid": "hamilton"
        },
        "key_39": {
          "name": "Grateful Dead",
          "artist_key": "2",
          "shows_key": "868",
          "showdate": "09/12/73",
          "venue": "William and Mary College Hall",
          "city": "Williamsburg",
          "state": "VA",
          "set1": [
            "Bertha",
            "Mexicali Blues",
            "Brown Eyed Women",
            "El Paso",
            "Don't Ease Me In",
            "Looks Like Rain",
            "Here Comes Sunshine",
            "Ramble On Rose",
            "Me & My Uncle",
            "Bird Song",
            "Jack Straw",
            "Loser",
            "Big River"
          ],
          "set2": [
            "Bertha",
            "Mexicali Blues",
            "Brown Eyed Women",
            "El Paso",
            "Don't Ease Me In",
            "Looks Like Rain",
            "Here Comes Sunshine",
            "Ramble On Rose",
            "Me & My Uncle",
            "Bird Song",
            "Jack Straw",
            "Loser",
            "Big River"
          ],
          "set3": "",
          "comment": "*with Martin Ffero and Joe Ellis on horns. Doug Salvn opened",
          "lastupdate": "1996-01-07 00:00:00",
          "showyear": "1973",
          "showsuserid": "system"
        },
        "key_40": {
          "name": "Grateful Dead",
          "artist_key": "2",
          "shows_key": "869",
          "showdate": "09/15/73",
          "venue": "Providence Civic Center",
          "city": "Providence",
          "state": "RI",
          "set1": [
            "Beat It On Down The Line",
            "Sugaree",
            "Greatest Story Ever Told",
            "Brown Eyed Women",
            "Me & My Uncle",
            "Ramble On Rose",
            "Looks Like Rain",
            "Deal",
            "Jack Straw",
            "Tennessee Jed",
            "El Paso",
            "Bird Song",
            "Playin' In The Band"
          ],
          "set2": [
            "Beat It On Down The Line",
            "Sugaree",
            "Greatest Story Ever Told",
            "Brown Eyed Women",
            "Me & My Uncle",
            "Ramble On Rose",
            "Looks Like Rain",
            "Deal",
            "Jack Straw",
            "Tennessee Jed",
            "El Paso",
            "Bird Song",
            "Playin' In The Band"
          ],
          "set3": "",
          "comment": "*with Martin Fiero and Joe Ellis on horns *Doug Sahm opened*",
          "lastupdate": "1996-01-07 00:00:00",
          "showyear": "1973",
          "showsuserid": "system"
        },
        "key_41": {
          "name": "Grateful Dead",
          "artist_key": "2",
          "shows_key": "870",
          "showdate": "09/17/73",
          "venue": "Onondaga County War Memorial",
          "city": "Syracuse",
          "state": "NY",
          "set1": [
            "Tennessee Jed",
            "Me & My Uncle",
            "They Love Each Other",
            "Beat It On Down The Line",
            "Sugaree",
            "Mexicali Blues",
            "Loser",
            "Looks Like Rain",
            "Row Jimmy",
            "Jack Straw",
            "Loose Lucy",
            "You Ain't Woman Enough",
            "Casey Jones"
          ],
          "set2": [
            "Tennessee Jed",
            "Me & My Uncle",
            "They Love Each Other",
            "Beat It On Down The Line",
            "Sugaree",
            "Mexicali Blues",
            "Loser",
            "Looks Like Rain",
            "Row Jimmy",
            "Jack Straw",
            "Loose Lucy",
            "You Ain't Woman Enough",
            "Casey Jones"
          ],
          "set3": "",
          "comment": "*with Martin Fiero and Joe Ellis on horns. Doug Sahm opened",
          "lastupdate": "1996-01-07 00:00:00",
          "showyear": "1973",
          "showsuserid": "hamilton"
        },
        "key_42": {
          "name": "Grateful Dead",
          "artist_key": "2",
          "shows_key": "871",
          "showdate": "09/18/73",
          "venue": "Onondaga County War Memorial",
          "city": "Syracuse",
          "state": "NY",
          "set1": "",
          "set2": "",
          "set3": "",
          "comment": "Doug Sahm opened",
          "lastupdate": "1996-01-07 00:00:00",
          "showyear": "1973",
          "showsuserid": "system"
        },
        "key_43": {
          "name": "Grateful Dead",
          "artist_key": "2",
          "shows_key": "872",
          "showdate": "09/20/73",
          "venue": "The Spectrum",
          "city": "Philadelphia",
          "state": "PA",
          "set1": [
            "Promised Land",
            "Tennessee Jed",
            "Mexicali Blues",
            "They Love Each Other",
            "Looks Like Rain",
            "Loser",
            "Beat It On Down The Line",
            "China Cat Sunflower-> I Know You Rider",
            "El Paso",
            "Row Jimmy",
            "Greatest Story Ever Told-> Deal",
            "Around & Around"
          ],
          "set2": [
            "Promised Land",
            "Tennessee Jed",
            "Mexicali Blues",
            "They Love Each Other",
            "Looks Like Rain",
            "Loser",
            "Beat It On Down The Line",
            "China Cat Sunflower-> I Know You Rider",
            "El Paso",
            "Row Jimmy",
            "Greatest Story Ever Told-> Deal",
            "Around & Around"
          ],
          "set3": "",
          "comment": "*with Martin Fiero and Joe Ellis on horns *Doug Sahm opened*",
          "lastupdate": "1996-01-07 00:00:00",
          "showyear": "1973",
          "showsuserid": "system"
        },
        "key_44": {
          "name": "Grateful Dead",
          "artist_key": "2",
          "shows_key": "873",
          "showdate": "09/21/73",
          "venue": "The Spectrum",
          "city": "Philadelphia",
          "state": "PA",
          "set1": [
            "Big Railroad Blues",
            "Me & My Uncle",
            "Brown Eyed Women",
            "Beat It On Down The Line",
            "Sugaree",
            "Big River",
            "Here Comes Sunshine",
            "El Paso",
            "Loose Lucy",
            "Jack Straw",
            "Black Peter",
            "Playin' In The Band"
          ],
          "set2": [
            "Big Railroad Blues",
            "Me & My Uncle",
            "Brown Eyed Women",
            "Beat It On Down The Line",
            "Sugaree",
            "Big River",
            "Here Comes Sunshine",
            "El Paso",
            "Loose Lucy",
            "Jack Straw",
            "Black Peter",
            "Playin' In The Band"
          ],
          "set3": "",
          "comment": "*with Martin Fiero and Joe Ellis on horns. Doug Sahm opened",
          "lastupdate": "1996-01-07 00:00:00",
          "showyear": "1973",
          "showsuserid": "system"
        },
        "key_45": {
          "name": "Grateful Dead",
          "artist_key": "2",
          "shows_key": "874",
          "showdate": "09/24/73",
          "venue": "Civic Arena",
          "city": "Pittsburgh",
          "state": "PA",
          "set1": [
            "Promised Land",
            "Sugaree",
            "Jack Straw",
            "They Love Each Other",
            "Mexicali Blues",
            "Loose Lucy",
            "Looks Like Rain",
            "Row Jimmy",
            "Big River",
            "China Cat Sunflower-> I Know You Rider",
            "Around & Around"
          ],
          "set2": [
            "Promised Land",
            "Sugaree",
            "Jack Straw",
            "They Love Each Other",
            "Mexicali Blues",
            "Loose Lucy",
            "Looks Like Rain",
            "Row Jimmy",
            "Big River",
            "China Cat Sunflower-> I Know You Rider",
            "Around & Around"
          ],
          "set3": "",
          "comment": "*with Martin Fiero and Joe Ellis on horns. Merry-Go-Round Broke Down' tuning before 'Greatest'. Doug Sahm opened",
          "lastupdate": "1996-01-07 00:00:00",
          "showyear": "1973",
          "showsuserid": "system"
        },
        "key_46": {
          "name": "Grateful Dead",
          "artist_key": "2",
          "shows_key": "875",
          "showdate": "09/26/73",
          "venue": "Community War Memorial Auditorium",
          "city": "Buffalo",
          "state": "NY",
          "set1": [
            "Here Comes Sunshine",
            "Beat It On Down The Line",
            "Deal",
            "Looks Like Rain",
            "Tennessee Jed",
            "Mexicali Blues",
            "Loser",
            "Big River",
            "Brown Eyed Women",
            "The Race Is On",
            "Row Jimmy",
            "El Paso",
            "China Cat Sunflower &gt; I Know You Rider",
            "Around And Around"
          ],
          "set2": [
            "Here Comes Sunshine",
            "Beat It On Down The Line",
            "Deal",
            "Looks Like Rain",
            "Tennessee Jed",
            "Mexicali Blues",
            "Loser",
            "Big River",
            "Brown Eyed Women",
            "The Race Is On",
            "Row Jimmy",
            "El Paso",
            "China Cat Sunflower &gt; I Know You Rider",
            "Around And Around"
          ],
          "set3": "",
          "comment": "* - w/ Martin Fierro And Joe Ellis On Horns",
          "lastupdate": "2012-09-23 00:07:32",
          "showyear": "1973",
          "showsuserid": "aikox2"
        },
        "key_47": {
          "name": "Grateful Dead",
          "artist_key": "2",
          "shows_key": "346547",
          "showdate": "10/04/73",
          "venue": "Cincinnati Gardens",
          "city": "Cincinnati",
          "state": "OH",
          "set1": [
            "Fragments of the show\r\nCasey Jones\r\nOne More Saturday Night"
          ],
          "set2": "",
          "set3": "",
          "comment": "",
          "lastupdate": "2006-12-07 15:13:03",
          "showyear": "1973",
          "showsuserid": "westcoastsails"
        },
        "key_48": {
          "name": "Grateful Dead",
          "artist_key": "2",
          "shows_key": "876",
          "showdate": "10/19/73",
          "venue": "Oklahoma City Fairgrounds Arena",
          "city": "Oklahoma City",
          "state": "OK",
          "set1": [
            "Promised Land",
            "Sugaree",
            "Mexicali Blues",
            "Tennessee Jed",
            "Looks Like Rain",
            "Don't Ease Me In",
            "Jack Straw",
            "They Love Each Other",
            "El Paso",
            "Row Jimmy",
            "Playin' In The Band"
          ],
          "set2": [
            "Promised Land",
            "Sugaree",
            "Mexicali Blues",
            "Tennessee Jed",
            "Looks Like Rain",
            "Don't Ease Me In",
            "Jack Straw",
            "They Love Each Other",
            "El Paso",
            "Row Jimmy",
            "Playin' In The Band"
          ],
          "set3": [
            "Promised Land",
            "Sugaree",
            "Mexicali Blues",
            "Tennessee Jed",
            "Looks Like Rain",
            "Don't Ease Me In",
            "Jack Straw",
            "They Love Each Other",
            "El Paso",
            "Row Jimmy",
            "Playin' In The Band"
          ],
          "comment": "*second encore. First \"Mind Left Body Jam\". This date is featured on <a href=\"mars.dead.net\"> Dick's Picks 19 </a>",
          "lastupdate": "2001-02-06 00:00:00",
          "showyear": "1973",
          "showsuserid": "diana"
        },
        "key_49": {
          "name": "Grateful Dead",
          "artist_key": "2",
          "shows_key": "877",
          "showdate": "10/21/73",
          "venue": "Omaha Civic Auditorium",
          "city": "Omaha",
          "state": "NE",
          "set1": [
            "Here Comes Sunshine",
            "Beat It On Down The Line",
            "Loser",
            "Black Throated Wind",
            "They Love Each Other",
            "Cumberland Blues",
            "El Paso",
            "You Ain't Woman Enough",
            "Weather Report Suite Prelude-> Weather Report Suite Part 1-> Let It Grow"
          ],
          "set2": [
            "Here Comes Sunshine",
            "Beat It On Down The Line",
            "Loser",
            "Black Throated Wind",
            "They Love Each Other",
            "Cumberland Blues",
            "El Paso",
            "You Ain't Woman Enough",
            "Weather Report Suite Prelude-> Weather Report Suite Part 1-> Let It Grow"
          ],
          "set3": "",
          "comment": "",
          "lastupdate": "1996-01-07 00:00:00",
          "showyear": "1973",
          "showsuserid": "system"
        },
        "key_50": {
          "name": "Grateful Dead",
          "artist_key": "2",
          "shows_key": "878",
          "showdate": "10/23/73",
          "venue": "Metropolitan Sports Center",
          "city": "Bloomington",
          "state": "MN",
          "set1": [
            "Promised Land",
            "Sugaree",
            "Mexicali Blues",
            "They Love Each Other",
            "Me And Bobby McGee",
            "Deal",
            "Black Throated Wind",
            "Brown Eyed Women",
            "Beat It On Down The Line",
            "Brokedown Palace",
            "Jack Straw",
            "China Cat Sunflower-> I Know You Rider",
            "Around & Around"
          ],
          "set2": [
            "Promised Land",
            "Sugaree",
            "Mexicali Blues",
            "They Love Each Other",
            "Me And Bobby McGee",
            "Deal",
            "Black Throated Wind",
            "Brown Eyed Women",
            "Beat It On Down The Line",
            "Brokedown Palace",
            "Jack Straw",
            "China Cat Sunflower-> I Know You Rider",
            "Around & Around"
          ],
          "set3": "",
          "comment": "",
          "lastupdate": "1996-01-07 00:00:00",
          "showyear": "1973",
          "showsuserid": "system"
        },
        "key_51": {
          "name": "Grateful Dead",
          "artist_key": "2",
          "shows_key": "879",
          "showdate": "10/25/73",
          "venue": "Dane County Coliseum",
          "city": "Madison",
          "state": "WI",
          "set1": [
            "Bertha",
            "Big River",
            "Here Comes Sunshine",
            "Black Throated Wind",
            "They Love Each Other",
            "Mexicali Blues",
            "Tennessee Jed",
            "Looks Like Rain",
            "Deal",
            "El Paso",
            "Row Jimmy",
            "Playing In The Band"
          ],
          "set2": [
            "Bertha",
            "Big River",
            "Here Comes Sunshine",
            "Black Throated Wind",
            "They Love Each Other",
            "Mexicali Blues",
            "Tennessee Jed",
            "Looks Like Rain",
            "Deal",
            "El Paso",
            "Row Jimmy",
            "Playing In The Band"
          ],
          "set3": "",
          "comment": "",
          "lastupdate": "2002-08-07 00:00:00",
          "showyear": "1973",
          "showsuserid": "hamilton"
        },
        "key_52": {
          "name": "Grateful Dead",
          "artist_key": "2",
          "shows_key": "880",
          "showdate": "10/27/73",
          "venue": "Indianapolis State Fair Coliseum",
          "city": "Indianapolis",
          "state": "IN",
          "set1": [
            "Promised Land",
            "Sugaree",
            "Mexicali Blues",
            "Loser",
            "Black Throated Wind",
            "They Love Each Other",
            "Jack Straw",
            "Ramble On Rose",
            "El Paso",
            "Brown Eyed Women",
            "Greatest Story Ever Told",
            "Loose Lucy",
            "Beat It On Down The Line",
            "China Cat Sunflower-> I Know You Rider"
          ],
          "set2": [
            "Promised Land",
            "Sugaree",
            "Mexicali Blues",
            "Loser",
            "Black Throated Wind",
            "They Love Each Other",
            "Jack Straw",
            "Ramble On Rose",
            "El Paso",
            "Brown Eyed Women",
            "Greatest Story Ever Told",
            "Loose Lucy",
            "Beat It On Down The Line",
            "China Cat Sunflower-> I Know You Rider"
          ],
          "set3": "",
          "comment": "",
          "lastupdate": "1996-01-07 00:00:00",
          "showyear": "1973",
          "showsuserid": "system"
        },
        "key_53": {
          "name": "Grateful Dead",
          "artist_key": "2",
          "shows_key": "881",
          "showdate": "10/29/73",
          "venue": "Kiel Auditorium",
          "city": "St. Louis",
          "state": "MO",
          "set1": [
            "Cold Rain & Snow",
            "Beat It On Down The Line",
            "Brown Eyed Women",
            "Mexicali Blues",
            "Don't Ease Me In",
            "Black Throated Wind",
            "Tennessee Jed",
            "The Race is On",
            "Row Jimmy",
            "El Paso",
            "Eyes Of The World-> China Doll",
            "Around & Around"
          ],
          "set2": [
            "Cold Rain & Snow",
            "Beat It On Down The Line",
            "Brown Eyed Women",
            "Mexicali Blues",
            "Don't Ease Me In",
            "Black Throated Wind",
            "Tennessee Jed",
            "The Race is On",
            "Row Jimmy",
            "El Paso",
            "Eyes Of The World-> China Doll",
            "Around & Around"
          ],
          "set3": "",
          "comment": "",
          "lastupdate": "1996-01-07 00:00:00",
          "showyear": "1973",
          "showsuserid": "system"
        },
        "key_54": {
          "name": "Grateful Dead",
          "artist_key": "2",
          "shows_key": "882",
          "showdate": "10/30/73",
          "venue": "Kiel Auditorium",
          "city": "St. Louis",
          "state": "MO",
          "set1": [
            "Here Comes Sunshine",
            "Me & My Uncle",
            "Ramble On Rose",
            "Looks Like Rain",
            "Deal",
            "Mexicali Blues",
            "They Love Each Other",
            "El Paso",
            "Row Jimmy",
            "Jack Straw",
            "China Cat Sunflower-> I Know You Rider",
            "Playin' In The Band"
          ],
          "set2": [
            "Here Comes Sunshine",
            "Me & My Uncle",
            "Ramble On Rose",
            "Looks Like Rain",
            "Deal",
            "Mexicali Blues",
            "They Love Each Other",
            "El Paso",
            "Row Jimmy",
            "Jack Straw",
            "China Cat Sunflower-> I Know You Rider",
            "Playin' In The Band"
          ],
          "set3": "",
          "comment": "",
          "lastupdate": "1996-01-07 00:00:00",
          "showyear": "1973",
          "showsuserid": "hamilton"
        },
        "key_55": {
          "name": "Grateful Dead",
          "artist_key": "2",
          "shows_key": "883",
          "showdate": "11/01/73",
          "venue": "McGaw Memorial Hall, Northwestern U.",
          "city": "Evanston",
          "state": "IL",
          "set1": [
            "The Promised Land",
            "Sugaree",
            "Me & Bobby McGee",
            "Brown-Eyed Women",
            "Black-Throated Wind",
            "China Cat Sunflower &gt; I Know You Rider",
            "Mexicali Blues",
            "Brokedown Palace",
            "Beat It On Down The Line",
            "Loose Lucy",
            "El Paso",
            "They Love Each Other",
            "Weather Report Suite Prelude &gt; Weather Report Suite Part 1 &gt; Let It Grow"
          ],
          "set2": [
            "The Promised Land",
            "Sugaree",
            "Me & Bobby McGee",
            "Brown-Eyed Women",
            "Black-Throated Wind",
            "China Cat Sunflower &gt; I Know You Rider",
            "Mexicali Blues",
            "Brokedown Palace",
            "Beat It On Down The Line",
            "Loose Lucy",
            "El Paso",
            "They Love Each Other",
            "Weather Report Suite Prelude &gt; Weather Report Suite Part 1 &gt; Let It Grow"
          ],
          "set3": "",
          "comment": "",
          "lastupdate": "2006-12-03 20:09:50",
          "showyear": "1973",
          "showsuserid": "captain_trip_420"
        },
        "key_56": {
          "name": "Grateful Dead",
          "artist_key": "2",
          "shows_key": "884",
          "showdate": "11/09/73",
          "venue": "Winterland Arena",
          "city": "San Francisco",
          "state": "CA",
          "set1": [
            "The Promised Land",
            "Brown Eyed Women",
            "Me & Bobby McGee",
            "They Love Each Other",
            "Black Throated Wind",
            "Don't Ease Me In",
            "Mexicali Blues",
            "Row Jimmy",
            "The Race Is On",
            "China Cat Sunflower > I Know You Rider",
            "Playing In The Band"
          ],
          "set2": [
            "The Promised Land",
            "Brown Eyed Women",
            "Me & Bobby McGee",
            "They Love Each Other",
            "Black Throated Wind",
            "Don't Ease Me In",
            "Mexicali Blues",
            "Row Jimmy",
            "The Race Is On",
            "China Cat Sunflower > I Know You Rider",
            "Playing In The Band"
          ],
          "set3": "",
          "comment": "",
          "lastupdate": "2002-08-07 00:00:00",
          "showyear": "1973",
          "showsuserid": "hamilton"
        },
        "key_57": {
          "name": "Grateful Dead",
          "artist_key": "2",
          "shows_key": "885",
          "showdate": "11/10/73",
          "venue": "Winterland Arena",
          "city": "San Francisco",
          "state": "CA",
          "set1": [
            "Bertha",
            "Jack Straw",
            "Loser",
            "Looks Like Rain",
            "Deal",
            "Mexicali Blues",
            "Tennessee Jed",
            "El Paso",
            "Brokedown Palace",
            "Beat It On Down The Line",
            "Row Jimmy",
            "Weather Report Suite Prelude-> Weather Report Suite Part 1-> Let It Grow"
          ],
          "set2": [
            "Bertha",
            "Jack Straw",
            "Loser",
            "Looks Like Rain",
            "Deal",
            "Mexicali Blues",
            "Tennessee Jed",
            "El Paso",
            "Brokedown Palace",
            "Beat It On Down The Line",
            "Row Jimmy",
            "Weather Report Suite Prelude-> Weather Report Suite Part 1-> Let It Grow"
          ],
          "set3": "",
          "comment": "Tico Tico' tuning before 'Playin",
          "lastupdate": "2001-11-09 00:00:00",
          "showyear": "1973",
          "showsuserid": "system"
        },
        "key_58": {
          "name": "Grateful Dead",
          "artist_key": "2",
          "shows_key": "886",
          "showdate": "11/11/73",
          "venue": "Winterland Arena",
          "city": "San Francisco",
          "state": "CA",
          "set1": [
            "Promised Land-> Bertha-> Greatest Story Ever Told",
            "Sugaree",
            "Black Throated Wind",
            "To Lay Me Down",
            "El Paso",
            "Ramble On Rose",
            "Me And Bobby McGee",
            "China Cat Sunflower-> I Know You Rider",
            "Me & My Uncle",
            "Loose Lucy",
            "Weather Report Suite Prelude-> Weather Report Suite Part 1-> Let It Grow"
          ],
          "set2": [
            "Promised Land-> Bertha-> Greatest Story Ever Told",
            "Sugaree",
            "Black Throated Wind",
            "To Lay Me Down",
            "El Paso",
            "Ramble On Rose",
            "Me And Bobby McGee",
            "China Cat Sunflower-> I Know You Rider",
            "Me & My Uncle",
            "Loose Lucy",
            "Weather Report Suite Prelude-> Weather Report Suite Part 1-> Let It Grow"
          ],
          "set3": "",
          "comment": "",
          "lastupdate": "1996-01-07 00:00:00",
          "showyear": "1973",
          "showsuserid": "brojay"
        },
        "key_59": {
          "name": "Grateful Dead",
          "artist_key": "2",
          "shows_key": "887",
          "showdate": "11/14/73",
          "venue": "San Diego Sports Arena",
          "city": "San Diego",
          "state": "CA",
          "set1": [
            "Big Railroad Blues",
            "Jack Straw",
            "Sugaree",
            "Mexicali Blues",
            "Here Comes Sunshine",
            "Black Throated Wind",
            "Cumberland Blues",
            "Row Jimmy",
            "The Race is On",
            "Brown Eyed Women",
            "Beat It On Down The Line",
            "Tennessee Jed",
            "El Paso",
            "China Cat Sunflower-> I Know You Rider",
            "Around & Around"
          ],
          "set2": [
            "Big Railroad Blues",
            "Jack Straw",
            "Sugaree",
            "Mexicali Blues",
            "Here Comes Sunshine",
            "Black Throated Wind",
            "Cumberland Blues",
            "Row Jimmy",
            "The Race is On",
            "Brown Eyed Women",
            "Beat It On Down The Line",
            "Tennessee Jed",
            "El Paso",
            "China Cat Sunflower-> I Know You Rider",
            "Around & Around"
          ],
          "set3": "",
          "comment": "",
          "lastupdate": "1996-01-07 00:00:00",
          "showyear": "1973",
          "showsuserid": "diana"
        },
        "key_60": {
          "name": "Grateful Dead",
          "artist_key": "2",
          "shows_key": "888",
          "showdate": "11/17/73",
          "venue": "Pauley Pavilion, UCLA",
          "city": "Los Angeles",
          "state": "CA",
          "set1": [
            "Me & My Uncle",
            "Here Comes Sunshine",
            "Looks Like Rain",
            "Deal",
            "Mexicali Blues",
            "Tennessee Jed",
            "The Race is On",
            "China Cat Sunflower-> I Know You Rider",
            "Big River",
            "Brown Eyed Women",
            "Around & Around"
          ],
          "set2": [
            "Me & My Uncle",
            "Here Comes Sunshine",
            "Looks Like Rain",
            "Deal",
            "Mexicali Blues",
            "Tennessee Jed",
            "The Race is On",
            "China Cat Sunflower-> I Know You Rider",
            "Big River",
            "Brown Eyed Women",
            "Around & Around"
          ],
          "set3": "",
          "comment": "",
          "lastupdate": "1996-01-07 00:00:00",
          "showyear": "1973",
          "showsuserid": "system"
        },
        "key_61": {
          "name": "Grateful Dead",
          "artist_key": "2",
          "shows_key": "889",
          "showdate": "11/20/73",
          "venue": "Denver Coliseum",
          "city": "Denver",
          "state": "CO",
          "set1": [
            "Ramble On Rose",
            "Mexicali",
            "Don't Ease Me In",
            "Black-Throated Wind",
            "Brown-Eyed Women",
            "Beat It On Down The Line",
            "To Lay Me Down",
            "The Race Is On",
            "They Love Each Other",
            "Me And Bobby McGee",
            "Tennessee Jed",
            "Big River",
            "Row Jimmy",
            "Weather Report Suite Prelude-> Weather Report Suite Part 1-> Let It Grow",
            "Casey Jones"
          ],
          "set2": [
            "Ramble On Rose",
            "Mexicali",
            "Don't Ease Me In",
            "Black-Throated Wind",
            "Brown-Eyed Women",
            "Beat It On Down The Line",
            "To Lay Me Down",
            "The Race Is On",
            "They Love Each Other",
            "Me And Bobby McGee",
            "Tennessee Jed",
            "Big River",
            "Row Jimmy",
            "Weather Report Suite Prelude-> Weather Report Suite Part 1-> Let It Grow",
            "Casey Jones"
          ],
          "set3": "",
          "comment": "SBD circulates in different order; AUD tape confirms above (see <a href= \"http://www.deadlists.com\">www.deadlists.com</a>)",
          "lastupdate": "2001-10-29 00:00:00",
          "showyear": "1973",
          "showsuserid": "hamilton"
        },
        "key_62": {
          "name": "Grateful Dead",
          "artist_key": "2",
          "shows_key": "890",
          "showdate": "11/21/73",
          "venue": "Denver Coliseum",
          "city": "Denver",
          "state": "CO",
          "set1": [
            "Me & My Uncle",
            "Sugaree",
            "Jack Straw",
            "Dire Wolf",
            "Black Throated Wind",
            "Big Railroad Blues",
            "Mexicali Blues",
            "They Love Each Other",
            "Looks Like Rain",
            "Here Comes Sunshine",
            "Big River",
            "Brokedown Palace",
            "Weather Report Suite Prelude-> Weather Report Suite Part 1-> Let It Grow"
          ],
          "set2": [
            "Me & My Uncle",
            "Sugaree",
            "Jack Straw",
            "Dire Wolf",
            "Black Throated Wind",
            "Big Railroad Blues",
            "Mexicali Blues",
            "They Love Each Other",
            "Looks Like Rain",
            "Here Comes Sunshine",
            "Big River",
            "Brokedown Palace",
            "Weather Report Suite Prelude-> Weather Report Suite Part 1-> Let It Grow"
          ],
          "set3": "",
          "comment": "",
          "lastupdate": "1996-01-07 00:00:00",
          "showyear": "1973",
          "showsuserid": "hamilton"
        },
        "key_63": {
          "name": "Grateful Dead",
          "artist_key": "2",
          "shows_key": "891",
          "showdate": "11/23/73",
          "venue": "County Coliseum",
          "city": "El Paso",
          "state": "TX",
          "set1": [
            "Bertha ; Mexicali Blues",
            "Deal",
            "Looks Like Rain",
            "Don't Ease Me In",
            "The \r\nRace Is On",
            "Loser",
            "Jack Straw",
            "; China Cat Sunflower > I Know You Rider ; E Paso",
            "Tennessee Jed",
            "Big River",
            "Row Jimmy",
            "Weather Report Suite Prelude > Weather Report Suite Part 1 > Let It Grow"
          ],
          "set2": [
            "Bertha ; Mexicali Blues",
            "Deal",
            "Looks Like Rain",
            "Don't Ease Me In",
            "The \r\nRace Is On",
            "Loser",
            "Jack Straw",
            "; China Cat Sunflower > I Know You Rider ; E Paso",
            "Tennessee Jed",
            "Big River",
            "Row Jimmy",
            "Weather Report Suite Prelude > Weather Report Suite Part 1 > Let It Grow"
          ],
          "set3": "",
          "comment": "",
          "lastupdate": "2002-03-24 00:00:00",
          "showyear": "1973",
          "showsuserid": "diana"
        },
        "key_64": {
          "name": "Grateful Dead",
          "artist_key": "2",
          "shows_key": "892",
          "showdate": "11/25/73",
          "venue": "Feyline Field",
          "city": "Tempe",
          "state": "AZ",
          "set1": [
            "Promised Land",
            "Sugaree",
            "Beat It On Down The Line",
            "Don't Ease Me In",
            "Black Throated Wind",
            "Tennessee Jed",
            "Mexicali Blues",
            "China Cat Sunflower-> I Know You Rider",
            "Big River",
            "Row Jimmy",
            "Me & My Uncle",
            "Brown Eyed Women",
            "Playin' In The Band"
          ],
          "set2": [
            "Promised Land",
            "Sugaree",
            "Beat It On Down The Line",
            "Don't Ease Me In",
            "Black Throated Wind",
            "Tennessee Jed",
            "Mexicali Blues",
            "China Cat Sunflower-> I Know You Rider",
            "Big River",
            "Row Jimmy",
            "Me & My Uncle",
            "Brown Eyed Women",
            "Playin' In The Band"
          ],
          "set3": "",
          "comment": "",
          "lastupdate": "2001-01-30 00:00:00",
          "showyear": "1973",
          "showsuserid": "hamilton"
        },
        "key_65": {
          "name": "Grateful Dead",
          "artist_key": "2",
          "shows_key": "46818",
          "showdate": "11/28/73",
          "venue": "Palace of Fine Arts",
          "city": "San Francisco",
          "state": "CA",
          "set1": "",
          "set2": "",
          "set3": "",
          "comment": "Seastones; a few separate sessions apparently may circulate under this date",
          "lastupdate": "2000-07-02 02:38:03",
          "showyear": "1973",
          "showsuserid": "hamilton"
        },
        "key_66": {
          "name": "Grateful Dead",
          "artist_key": "2",
          "shows_key": "893",
          "showdate": "11/30/73",
          "venue": "Music Hall",
          "city": "Boston",
          "state": "MA",
          "set1": [
            "Morning Dew",
            "Mexicali Blues",
            "Dire Wolf",
            "Beat It On Down The Line",
            "Brown Eyed Women",
            "Black Throated Wind",
            "Don't Ease Me In",
            "El Paso",
            "They Love Each Other",
            "Big River",
            "Loser",
            "Playin' In The Band"
          ],
          "set2": [
            "Morning Dew",
            "Mexicali Blues",
            "Dire Wolf",
            "Beat It On Down The Line",
            "Brown Eyed Women",
            "Black Throated Wind",
            "Don't Ease Me In",
            "El Paso",
            "They Love Each Other",
            "Big River",
            "Loser",
            "Playin' In The Band"
          ],
          "set3": "",
          "comment": "This date is featured on <a href= \"http://mars.dead.net\">Dick's Picks 14</a>.",
          "lastupdate": "2008-10-07 16:05:08",
          "showyear": "1973",
          "showsuserid": "system"
        },
        "key_67": {
          "name": "Grateful Dead",
          "artist_key": "2",
          "shows_key": "894",
          "showdate": "12/01/73",
          "venue": "Music Hall",
          "city": "Boston",
          "state": "MA",
          "set1": [
            "Promised Land",
            "Sugaree",
            "Mexicali Blues",
            "Tennessee Jed",
            "Looks Like Rain",
            "China Cat Sunflower-> I Know You Rider",
            "Big River",
            "Brokedown Palace",
            "Weather Report Suite Prelude-> Weather Report Suite Part 1-> Let It Grow",
            "Casey Jones"
          ],
          "set2": [
            "Promised Land",
            "Sugaree",
            "Mexicali Blues",
            "Tennessee Jed",
            "Looks Like Rain",
            "China Cat Sunflower-> I Know You Rider",
            "Big River",
            "Brokedown Palace",
            "Weather Report Suite Prelude-> Weather Report Suite Part 1-> Let It Grow",
            "Casey Jones"
          ],
          "set3": "",
          "comment": "",
          "lastupdate": "2008-10-07 16:05:14",
          "showyear": "1973",
          "showsuserid": "system"
        },
        "key_68": {
          "name": "Grateful Dead",
          "artist_key": "2",
          "shows_key": "895",
          "showdate": "12/02/73",
          "venue": "Music Hall",
          "city": "Boston",
          "state": "MA",
          "set1": [
            "Cold Rain & Snow",
            "Beat It On Down The Line",
            "Dire Wolf",
            "The Race is On",
            "Brown Eyed Women",
            "Jack Straw",
            "Ramble On Rose",
            "El Paso",
            "Row Jimmy",
            "Big River",
            "Deal",
            "Weather Report Suite Prelude-> Weather Report Suite Part 1-> Let It Grow"
          ],
          "set2": [
            "Cold Rain & Snow",
            "Beat It On Down The Line",
            "Dire Wolf",
            "The Race is On",
            "Brown Eyed Women",
            "Jack Straw",
            "Ramble On Rose",
            "El Paso",
            "Row Jimmy",
            "Big River",
            "Deal",
            "Weather Report Suite Prelude-> Weather Report Suite Part 1-> Let It Grow"
          ],
          "set3": "",
          "comment": "'Merry-Go-Round Broke Down' & 'Beer Barrel Polka' tunings before 'Jack Straw\". This date is featured on <a href= \"http://mars.dead.net\">Dick's Picks 14</a>.",
          "lastupdate": "2008-10-07 16:05:37",
          "showyear": "1973",
          "showsuserid": "system"
        },
        "key_69": {
          "name": "Grateful Dead",
          "artist_key": "2",
          "shows_key": "896",
          "showdate": "12/04/73",
          "venue": "Cincinnati Gardens",
          "city": "Cincinnati",
          "state": "OH",
          "set1": [
            "Johnny B. Goode",
            "Sugaree",
            "Me & My Uncle",
            "China Cat Sunflower-> I Know You Rider",
            "El Paso",
            "Deal",
            "Big River",
            "Tennessee Jed",
            "Truckin'-> Stella Blue",
            "Around & Around"
          ],
          "set2": [
            "Johnny B. Goode",
            "Sugaree",
            "Me & My Uncle",
            "China Cat Sunflower-> I Know You Rider",
            "El Paso",
            "Deal",
            "Big River",
            "Tennessee Jed",
            "Truckin'-> Stella Blue",
            "Around & Around"
          ],
          "set3": "",
          "comment": "",
          "lastupdate": "1996-01-07 00:00:00",
          "showyear": "1973",
          "showsuserid": "system"
        },
        "key_70": {
          "name": "Grateful Dead",
          "artist_key": "2",
          "shows_key": "897",
          "showdate": "12/06/73",
          "venue": "Public Hall",
          "city": "Cleveland",
          "state": "OH",
          "set1": [
            "Bertha",
            "Mexicali Blues",
            "Loser",
            "Black Throated Wind",
            "They Love Each Other",
            "Beat It On Down The Line",
            "Deal",
            "El Paso",
            "Row Jimmy",
            "Greatest Story Ever Told",
            "China Cat Sunflower > I Know You Rider",
            "Around And Around"
          ],
          "set2": [
            "Bertha",
            "Mexicali Blues",
            "Loser",
            "Black Throated Wind",
            "They Love Each Other",
            "Beat It On Down The Line",
            "Deal",
            "El Paso",
            "Row Jimmy",
            "Greatest Story Ever Told",
            "China Cat Sunflower > I Know You Rider",
            "Around And Around"
          ],
          "set3": "",
          "comment": "2nd set includes the longest ever Here Comes Sunshine (15'38) and the 3rd longest ever Dark Star (43'28)\r\nupdated venue and setlist courtesy <a href= \"http://www.deadlists.com\">Deadlists</a>",
          "lastupdate": "2001-06-23 00:00:00",
          "showyear": "1973",
          "showsuserid": "greenone"
        },
        "key_71": {
          "name": "Grateful Dead",
          "artist_key": "2",
          "shows_key": "898",
          "showdate": "12/08/73",
          "venue": "Cameron Indoor Stadium, Duke U",
          "city": "Durham",
          "state": "NC",
          "set1": [
            "Me & My Uncle",
            "Sugaree",
            "Mexicali Blues",
            "Dire Wolf",
            "Black Throated Wind",
            "They Love Each Other",
            "Me And Bobby McGee",
            "Don't Ease Me In",
            "The Race Is On",
            "Brown Eyed Women",
            "Big River",
            "Candyman",
            "Weather Report Suite Prelude > Weather Report Suite Part 1 > Let It Grow",
            "China Cat Sunflower > I Know You Rider"
          ],
          "set2": [
            "Me & My Uncle",
            "Sugaree",
            "Mexicali Blues",
            "Dire Wolf",
            "Black Throated Wind",
            "They Love Each Other",
            "Me And Bobby McGee",
            "Don't Ease Me In",
            "The Race Is On",
            "Brown Eyed Women",
            "Big River",
            "Candyman",
            "Weather Report Suite Prelude > Weather Report Suite Part 1 > Let It Grow",
            "China Cat Sunflower > I Know You Rider"
          ],
          "set3": "",
          "comment": "",
          "lastupdate": "2003-05-13 00:00:00",
          "showyear": "1973",
          "showsuserid": "hamilton"
        },
        "key_72": {
          "name": "Grateful Dead",
          "artist_key": "2",
          "shows_key": "899",
          "showdate": "12/10/73",
          "venue": "Charlotte Coliseum",
          "city": "Charlotte",
          "state": "NC",
          "set1": [
            "Bertha \nMexicali Blues \nDeal  \nBig River  \nDon't Ease Me In \nPlaying In The Band \nPromised Land  \nPeggy-O\nRow Jimmy  \nMe And Bobby McGee  \nBig Railroad Blues"
          ],
          "set2": [
            "Bertha \nMexicali Blues \nDeal  \nBig River  \nDon't Ease Me In \nPlaying In The Band \nPromised Land  \nPeggy-O\nRow Jimmy  \nMe And Bobby McGee  \nBig Railroad Blues"
          ],
          "set3": "",
          "comment": "",
          "lastupdate": "2007-08-22 18:40:35",
          "showyear": "1973",
          "showsuserid": "aikox2"
        },
        "key_73": {
          "name": "Grateful Dead",
          "artist_key": "2",
          "shows_key": "900",
          "showdate": "12/12/73",
          "venue": "The Omni",
          "city": "Atlanta",
          "state": "GA",
          "set1": [
            "The Promised Land",
            "Sugaree",
            "Mexicali Blues",
            "Tennessee Jed",
            "Jack Straw",
            "Don't Ease Me In",
            "Looks Like Rain",
            "They Love Each Other",
            "El Paso",
            "Peggy-O",
            "Beat It On Down The Line",
            "Brown Eyed Women",
            "Big River",
            "Deal",
            "Playing In The Band"
          ],
          "set2": [
            "The Promised Land",
            "Sugaree",
            "Mexicali Blues",
            "Tennessee Jed",
            "Jack Straw",
            "Don't Ease Me In",
            "Looks Like Rain",
            "They Love Each Other",
            "El Paso",
            "Peggy-O",
            "Beat It On Down The Line",
            "Brown Eyed Women",
            "Big River",
            "Deal",
            "Playing In The Band"
          ],
          "set3": "",
          "comment": "Sound check: Sleigh Ride. Rip It Up. Blue Suede Shoes. Peggy-O, Jack Straw, Cumberland Blues, 30 Days",
          "lastupdate": "2012-09-17 00:41:57",
          "showyear": "1973",
          "showsuserid": "aikox2"
        },
        "key_74": {
          "name": "Grateful Dead",
          "artist_key": "2",
          "shows_key": "901",
          "showdate": "12/18/73",
          "venue": "Curtis Hixon Convention Hall",
          "city": "Tampa",
          "state": "FL",
          "set1": [
            "Tennessee Jed",
            "Me & My Uncle",
            "Don't Ease Me In",
            "Looks Like Rain",
            "They Love Each Other",
            "Me And Bobby McGee",
            "Brown Eyed Women",
            "Beat It On Down The Line-> Peggy-O",
            "El Paso",
            "Deal",
            "Jack Straw",
            "China Cat Sunflower-> I Know You Rider"
          ],
          "set2": [
            "Tennessee Jed",
            "Me & My Uncle",
            "Don't Ease Me In",
            "Looks Like Rain",
            "They Love Each Other",
            "Me And Bobby McGee",
            "Brown Eyed Women",
            "Beat It On Down The Line-> Peggy-O",
            "El Paso",
            "Deal",
            "Jack Straw",
            "China Cat Sunflower-> I Know You Rider"
          ],
          "set3": "",
          "comment": "",
          "lastupdate": "1996-01-07 00:00:00",
          "showyear": "1973",
          "showsuserid": "diana"
        },
        "key_75": {
          "name": "Grateful Dead",
          "artist_key": "2",
          "shows_key": "902",
          "showdate": "12/19/73",
          "venue": "Curtis Hixon Convention Hall",
          "city": "Tampa",
          "state": "FL",
          "set1": [
            "Promised Land \nSugaree\nMexicali Blues \nDire Wolf\nBlack Throated Wind \nCandyman \nJack Straw\nBig Railroad Blues \nBig River\nHere Comes Sunshine \nEl Paso\nRamble On Rose\nPlayin' In The Band"
          ],
          "set2": [
            "Promised Land \nSugaree\nMexicali Blues \nDire Wolf\nBlack Throated Wind \nCandyman \nJack Straw\nBig Railroad Blues \nBig River\nHere Comes Sunshine \nEl Paso\nRamble On Rose\nPlayin' In The Band"
          ],
          "set3": "",
          "comment": "This date is featured on <a href= \"http://mars.dead.net\">Dick's Picks 1</a>.",
          "lastupdate": "2009-05-06 06:17:02",
          "showyear": "1973",
          "showsuserid": "mgiaco"
        },
        "key_76": {
          "name": "Grateful Dead",
          "artist_key": "2",
          "shows_key": "147731",
          "showdate": "12/??/73",
          "venue": "Unsurpassed Masters Vol. 7",
          "city": "Compilation",
          "state": "Compilation",
          "set1": [
            "\"Unsurpassed Vol. 7\"           (1cd) 'A' to 'B+'   \r\nTracks 1-6 are from 12/12/73 soundcheck\r\nTracks 7-16 are Garcia \"Compliments\" outtakes\r\n1.Rip It Up   2.Blue Suede Shoes   3.Peggy-O   4.Jack Straw   5.Cumberland Blues   \r\n6. 30 Days  7.Turn on the Bright Lights   8.Spend the Night Together   9.Nothing Without Love \r\n10.That's What Love Will Make You Do   11.Let It Rock  12.Roadrunner  13-15.unknown  \r\n16.I Saw Her Standing There   17.Let it Grow   18.They Love Each Other   19.Wave That Flag"
          ],
          "set2": "",
          "set3": "",
          "comment": "GD Unsurpassed Vol 7",
          "lastupdate": "2006-09-14 14:31:57",
          "showyear": "1973",
          "showsuserid": "keithcdr"
        },
        "key_77": {
          "name": "Grateful Dead",
          "artist_key": "2",
          "shows_key": "226857",
          "showdate": "??/??/73",
          "venue": "Studio Rehearsals",
          "city": "Various",
          "state": "CA",
          "set1": [
            "<b>Admin work in progress:</b>\r\npossible placeholder for:\r\ncomment:\r\nunknown date and location; studio outtakes; sbd>?>cassette>wav>shn\r\ncirc date: 1/30/04"
          ],
          "set2": [
            "<b>Admin work in progress:</b>\r\npossible placeholder for:\r\ncomment:\r\nunknown date and location; studio outtakes; sbd>?>cassette>wav>shn\r\ncirc date: 1/30/04"
          ],
          "set3": [
            "<b>Admin work in progress:</b>\r\npossible placeholder for:\r\ncomment:\r\nunknown date and location; studio outtakes; sbd>?>cassette>wav>shn\r\ncirc date: 1/30/04"
          ],
          "comment": "submitter contact: SeanCheadle (profstoneATearthlinkDOTnet)",
          "lastupdate": "2005-12-21 21:25:24",
          "showyear": "1973",
          "showsuserid": "hamilton"
        }
      },
      "status": "success"
    }
  }
}