{
  "db_rest": {
    "@generator": "zend",
    "@version": "1.0",
    "fetchArtistYear": {
      "shows": {
        "key_0": {
          "name": "Grateful Dead",
          "artist_key": "2",
          "shows_key": "183194",
          "showdate": "01/02/74",
          "venue": "Bootleg \"Unsurpassed Vol. 8\"",
          "city": "San Francisco",
          "state": "CA",
          "set1": [
            "1974 \"Mars Hotel\" Rehearsals \r\n1. Pride Of Cucamonga #1 > Pride Of Cucamonga #2 6:40 \r\n2. Money Money 5:41 \r\n3.Unbroken Chain #1 > \r\nUnbroken Chain #2 8:03 \r\n4. Unbroken Chain (acoustic) 6:19 Phil Teaching the Band!\r\n1974 \"Mars Hotel\" Demos ; All Instrumental \r\n5. Unbroken Chain 6:46 \r\n6. Scarlet Begonias 8:45 \r\n7. Pride Of Cucamonga 5:00 \r\n8. Ship Of Fools 4:25 \r\n9. Money Money 7:54 \r\n10. Loose Lucy 6:21 \r\nTotal Time 65:59"
          ],
          "set2": "",
          "set3": "",
          "comment": "",
          "lastupdate": "2003-11-18 10:32:52",
          "showyear": "1974",
          "showsuserid": "okcomputerboy"
        },
        "key_1": {
          "name": "Grateful Dead",
          "artist_key": "2",
          "shows_key": "311587",
          "showdate": "02/02/74",
          "venue": "Unknown",
          "city": "Unknown",
          "state": "Unknown",
          "set1": "",
          "set2": "",
          "set3": "",
          "comment": "",
          "lastupdate": "2006-03-29 17:54:48",
          "showyear": "1974",
          "showsuserid": "tpcreed"
        },
        "key_2": {
          "name": "Grateful Dead",
          "artist_key": "2",
          "shows_key": "903",
          "showdate": "02/22/74",
          "venue": "Winterland Arena",
          "city": "San Francisco",
          "state": "CA",
          "set1": [
            "U.S. Blues",
            "Beat It On Down The Line",
            "Brown Eyed Women",
            "Mexicali Blues",
            "It Must Have Been The Roses",
            "Black Throated Wind",
            "They Love Each Other",
            "Big River",
            "Loose Lucy",
            "El Paso",
            "Row Jimmy",
            "Playin' In The Band"
          ],
          "set2": [
            "U.S. Blues",
            "Beat It On Down The Line",
            "Brown Eyed Women",
            "Mexicali Blues",
            "It Must Have Been The Roses",
            "Black Throated Wind",
            "They Love Each Other",
            "Big River",
            "Loose Lucy",
            "El Paso",
            "Row Jimmy",
            "Playin' In The Band"
          ],
          "set3": [
            "U.S. Blues",
            "Beat It On Down The Line",
            "Brown Eyed Women",
            "Mexicali Blues",
            "It Must Have Been The Roses",
            "Black Throated Wind",
            "They Love Each Other",
            "Big River",
            "Loose Lucy",
            "El Paso",
            "Row Jimmy",
            "Playin' In The Band"
          ],
          "comment": "Reported Soundcheck before this show, which may also circulate, possibly misdated, as 2/24/74: Let It Grow, They Love Each Other, U. S. Blues #1 -> U. S. Blues #2, Attics Of My Life, It Must Have Been The Roses -> Jam",
          "lastupdate": "2002-04-02 00:00:00",
          "showyear": "1974",
          "showsuserid": "stark1"
        },
        "key_3": {
          "name": "Grateful Dead",
          "artist_key": "2",
          "shows_key": "904",
          "showdate": "02/23/74",
          "venue": "Winterland Arena",
          "city": "San Francisco",
          "state": "CA",
          "set1": [
            "Around & Around",
            "Dire Wolf",
            "Me And Bobby McGee",
            "Sugaree",
            "Mexicali Blues",
            "Here Comes Sunshine",
            "Beat It On Down The Line",
            "Ship of Fools",
            "Jack Straw",
            "Deal",
            "Promised Land-> Bertha-> Greatest Story Ever Told"
          ],
          "set2": [
            "Around & Around",
            "Dire Wolf",
            "Me And Bobby McGee",
            "Sugaree",
            "Mexicali Blues",
            "Here Comes Sunshine",
            "Beat It On Down The Line",
            "Ship of Fools",
            "Jack Straw",
            "Deal",
            "Promised Land-> Bertha-> Greatest Story Ever Told"
          ],
          "set3": "",
          "comment": "**Second Encore *Slipknot Intro",
          "lastupdate": "1996-01-07 00:00:00",
          "showyear": "1974",
          "showsuserid": "system"
        },
        "key_4": {
          "name": "Grateful Dead",
          "artist_key": "2",
          "shows_key": "905",
          "showdate": "02/24/74",
          "venue": "Winterland Arena",
          "city": "San Francisco",
          "state": "CA",
          "set1": [
            "U.S. Blues",
            "Mexicali Blues",
            "Brown Eyed Women",
            "Beat It On Down The Line",
            "Candyman",
            "Jack Straw",
            "China Cat Sunflower &gt; I Know You Rider",
            "El Paso",
            "Loser",
            "Playin' In The Band"
          ],
          "set2": [
            "U.S. Blues",
            "Mexicali Blues",
            "Brown Eyed Women",
            "Beat It On Down The Line",
            "Candyman",
            "Jack Straw",
            "China Cat Sunflower &gt; I Know You Rider",
            "El Paso",
            "Loser",
            "Playin' In The Band"
          ],
          "set3": "",
          "comment": "",
          "lastupdate": "2011-10-27 14:23:32",
          "showyear": "1974",
          "showsuserid": "charliemiller"
        },
        "key_5": {
          "name": "Grateful Dead",
          "artist_key": "2",
          "shows_key": "71322",
          "showdate": "02/24/74",
          "venue": "Winterland Arena- soundcheck",
          "city": "San Francisco",
          "state": "CA",
          "set1": [
            "Let It Grow",
            "They Love Each Other Let It Grow",
            "They Love Each Other",
            "U. S. Blues #1 -> U. S. Blues #2",
            "Attics Of My Life",
            "It Must Have Been The Roses -> Jam"
          ],
          "set2": "",
          "set3": "",
          "comment": "Material has been circulated as this date via a 2001 shn set, but is more likely a mislabel of what is really 2/22/74 soundcheck",
          "lastupdate": "2002-06-13 18:16:19",
          "showyear": "1974",
          "showsuserid": "hamilton"
        },
        "key_6": {
          "name": "Grateful Dead",
          "artist_key": "2",
          "shows_key": "906",
          "showdate": "03/23/74",
          "venue": "Cow Palace",
          "city": "Daly City",
          "state": "CA",
          "set1": [
            "U.S. Blues",
            "Promised Land",
            "Brown Eyed Women",
            "Mexicali Blues",
            "Tennessee Jed",
            "Black Throated Wind",
            "Scarlet Begonias",
            "Beat It On Down The Line",
            "It Must Have Been The Roses",
            "El Paso",
            "Deal",
            "Cassidy",
            "China Cat Sunflower-> I Know You Rider",
            "Weather Report Suite Prelude-> Weather Report Suite Part 1-> Let It Grow"
          ],
          "set2": [
            "U.S. Blues",
            "Promised Land",
            "Brown Eyed Women",
            "Mexicali Blues",
            "Tennessee Jed",
            "Black Throated Wind",
            "Scarlet Begonias",
            "Beat It On Down The Line",
            "It Must Have Been The Roses",
            "El Paso",
            "Deal",
            "Cassidy",
            "China Cat Sunflower-> I Know You Rider",
            "Weather Report Suite Prelude-> Weather Report Suite Part 1-> Let It Grow"
          ],
          "set3": "",
          "comment": "material from this date is featured on Dick's Picks 24- <a href= \"http://mars.dead.net\">go buy it</a>",
          "lastupdate": "2002-03-11 00:00:00",
          "showyear": "1974",
          "showsuserid": "system"
        },
        "key_7": {
          "name": "Grateful Dead",
          "artist_key": "2",
          "shows_key": "106069",
          "showdate": "03/25/74",
          "venue": "Wally Heiders Studio (Mars Hotel outtakes)",
          "city": "San Francisco",
          "state": "CA",
          "set1": [
            "-Unbroken Chain Instrumental (Reel wow & fluter",
            "Minor distortion)\r\n-Scarlet Begonias Instrumental (Drop Out 2:36)\r\n-Pride Of Cucamongo Instrumental\r\n-Ship Of Fools Instrumental w/ Acoustic\r\n-Money Honey Instrumental\r\n-Loose Lucy Instrumental\r\n-US Blues Instrumental\r\nFiller:\r\nEarly Crazy Fingers 6-3-75 Ace's Mill Valley"
          ],
          "set2": "",
          "set3": "",
          "comment": "Studio Instumental Roughs From Vault Reel Marked \"3-74\"",
          "lastupdate": "2003-05-22 06:09:15",
          "showyear": "1974",
          "showsuserid": "rodiebluez"
        },
        "key_8": {
          "name": "Grateful Dead",
          "artist_key": "2",
          "shows_key": "907",
          "showdate": "05/12/74",
          "venue": "University of Nevada",
          "city": "Reno",
          "state": "NV",
          "set1": [
            "Promised Land",
            "Beer Barrel Polka",
            "Tennessee Jed",
            "Jack Straw",
            "Brown Eyed Women",
            "Beat It on Down the Line",
            "China Cat Sunflower-> I Know You Rider",
            "El Paso",
            "U.S. Blues",
            "Greatest Story Ever Told",
            "It Must Have Been The Roses",
            "Me And Bobby McGee",
            "Deal"
          ],
          "set2": [
            "Promised Land",
            "Beer Barrel Polka",
            "Tennessee Jed",
            "Jack Straw",
            "Brown Eyed Women",
            "Beat It on Down the Line",
            "China Cat Sunflower-> I Know You Rider",
            "El Paso",
            "U.S. Blues",
            "Greatest Story Ever Told",
            "It Must Have Been The Roses",
            "Me And Bobby McGee",
            "Deal"
          ],
          "set3": "",
          "comment": "",
          "lastupdate": "2001-11-02 00:00:00",
          "showyear": "1974",
          "showsuserid": "hamilton"
        },
        "key_9": {
          "name": "Grateful Dead",
          "artist_key": "2",
          "shows_key": "908",
          "showdate": "05/14/74",
          "venue": "Adams Field House, U of Montana",
          "city": "Missoula",
          "state": "MT",
          "set1": [
            "Bertha",
            "Me & My Uncle",
            "Loser",
            "Black Throated Wind",
            "Scarlet Begonias",
            "It Must Have Been The Roses",
            "Jack Straw",
            "Tennessee Jed",
            "Deal",
            "Big River",
            "Brown Eyed Women",
            "Playin' In The Band"
          ],
          "set2": [
            "Bertha",
            "Me & My Uncle",
            "Loser",
            "Black Throated Wind",
            "Scarlet Begonias",
            "It Must Have Been The Roses",
            "Jack Straw",
            "Tennessee Jed",
            "Deal",
            "Big River",
            "Brown Eyed Women",
            "Playin' In The Band"
          ],
          "set3": "",
          "comment": "",
          "lastupdate": "2014-06-03 18:13:31",
          "showyear": "1974",
          "showsuserid": "duggy"
        },
        "key_10": {
          "name": "Grateful Dead",
          "artist_key": "2",
          "shows_key": "909",
          "showdate": "05/17/74",
          "venue": "P.N.E. Coliseum",
          "city": "Vancouver",
          "state": "BC",
          "set1": [
            "Promised Land",
            "Deal",
            "The Race is On",
            "Ramble On Rose",
            "Jack Straw",
            "Dire Wolf",
            "Beat It On Down The Line",
            "Loose Lucy",
            "Big River",
            "It Must Have Been The Roses",
            "Mexicali Blues",
            "Row Jimmy",
            "Playin' In The Band"
          ],
          "set2": [
            "Promised Land",
            "Deal",
            "The Race is On",
            "Ramble On Rose",
            "Jack Straw",
            "Dire Wolf",
            "Beat It On Down The Line",
            "Loose Lucy",
            "Big River",
            "It Must Have Been The Roses",
            "Mexicali Blues",
            "Row Jimmy",
            "Playin' In The Band"
          ],
          "set3": "",
          "comment": "",
          "lastupdate": "2002-11-06 00:00:00",
          "showyear": "1974",
          "showsuserid": "hamilton"
        },
        "key_11": {
          "name": "Grateful Dead",
          "artist_key": "2",
          "shows_key": "910",
          "showdate": "05/19/74",
          "venue": "Portland Memorial Coliseum",
          "city": "Portland",
          "state": "OR",
          "set1": [
            "Mississippi Half-Step Uptown Toodeloo",
            "Mexicali Blues",
            "Big Railroad Blues",
            "Black Throated Wind",
            "Scarlet Begonias",
            "Beat It On Down The Line",
            "Tennessee Jed",
            "Me And Bobby McGee",
            "Sugaree",
            "Jack Straw",
            "It Must Have Been The Roses",
            "El Paso",
            "Loose Lucy",
            "Money Money",
            "China Cat Sunflower &gt; I Know You Rider"
          ],
          "set2": [
            "Mississippi Half-Step Uptown Toodeloo",
            "Mexicali Blues",
            "Big Railroad Blues",
            "Black Throated Wind",
            "Scarlet Begonias",
            "Beat It On Down The Line",
            "Tennessee Jed",
            "Me And Bobby McGee",
            "Sugaree",
            "Jack Straw",
            "It Must Have Been The Roses",
            "El Paso",
            "Loose Lucy",
            "Money Money",
            "China Cat Sunflower &gt; I Know You Rider"
          ],
          "set3": "",
          "comment": "",
          "lastupdate": "2010-03-25 00:43:53",
          "showyear": "1974",
          "showsuserid": "gold soundz"
        },
        "key_12": {
          "name": "Grateful Dead",
          "artist_key": "2",
          "shows_key": "911",
          "showdate": "05/21/74",
          "venue": "Edmundson Pavilion, U of Washington",
          "city": "Seattle",
          "state": "WA",
          "set1": [
            "Me & My Uncle",
            "Brown Eyed Women",
            "Beat It On Down The Line",
            "Deal",
            "Mexicali Blues",
            "It Must Have Been The Roses",
            "The Race is On",
            "Scarlet Begonias",
            "El Paso",
            "Row Jimmy",
            "Money Money",
            "Ship of Fools",
            "Weather Report Suite Prelude-> Weather Report Suite Part 1-> Let It Grow-> China Doll"
          ],
          "set2": [
            "Me & My Uncle",
            "Brown Eyed Women",
            "Beat It On Down The Line",
            "Deal",
            "Mexicali Blues",
            "It Must Have Been The Roses",
            "The Race is On",
            "Scarlet Begonias",
            "El Paso",
            "Row Jimmy",
            "Money Money",
            "Ship of Fools",
            "Weather Report Suite Prelude-> Weather Report Suite Part 1-> Let It Grow-> China Doll"
          ],
          "set3": "",
          "comment": "",
          "lastupdate": "1996-01-07 00:00:00",
          "showyear": "1974",
          "showsuserid": "system"
        },
        "key_13": {
          "name": "Grateful Dead",
          "artist_key": "2",
          "shows_key": "912",
          "showdate": "05/25/74",
          "venue": "Campus Stadium, UC Santa Barbara",
          "city": "Goleta",
          "state": "CA",
          "set1": [
            "U.S. Blues",
            "Mexicali Blues",
            "Deal",
            "Jack Straw",
            "Scarlet Begonias",
            "Beat It On Down The Line",
            "Brown Eyed Women",
            "Me & My Uncle",
            "Sugaree",
            "El Paso",
            "China Cat Sunflower-> I Know You Rider",
            "Around & Around"
          ],
          "set2": [
            "U.S. Blues",
            "Mexicali Blues",
            "Deal",
            "Jack Straw",
            "Scarlet Begonias",
            "Beat It On Down The Line",
            "Brown Eyed Women",
            "Me & My Uncle",
            "Sugaree",
            "El Paso",
            "China Cat Sunflower-> I Know You Rider",
            "Around & Around"
          ],
          "set3": "",
          "comment": "Other artist(s): Maria Muldar, Great American String Band, Elvin Bishop",
          "lastupdate": "1996-01-07 00:00:00",
          "showyear": "1974",
          "showsuserid": "system"
        },
        "key_14": {
          "name": "Grateful Dead",
          "artist_key": "2",
          "shows_key": "913",
          "showdate": "06/08/74",
          "venue": "Oakland-Alameda County Coliseum",
          "city": "Oakland",
          "state": "CA",
          "set1": [
            "Promised Land",
            "Brown Eyed Women",
            "Me And Bobby McGee",
            "Scarlet Begonias",
            "Mexicali Blues",
            "It Must Have Been The Roses",
            "Me & My Uncle",
            "Tennessee Jed",
            "Greatest Story Ever Told",
            "China Cat Sunflower-> I Know You Rider",
            "Around & Around"
          ],
          "set2": [
            "Promised Land",
            "Brown Eyed Women",
            "Me And Bobby McGee",
            "Scarlet Begonias",
            "Mexicali Blues",
            "It Must Have Been The Roses",
            "Me & My Uncle",
            "Tennessee Jed",
            "Greatest Story Ever Told",
            "China Cat Sunflower-> I Know You Rider",
            "Around & Around"
          ],
          "set3": "",
          "comment": "Other artist(s): Beach Boys, NRPS, Commander Cody",
          "lastupdate": "1996-01-07 00:00:00",
          "showyear": "1974",
          "showsuserid": "system"
        },
        "key_15": {
          "name": "Grateful Dead",
          "artist_key": "2",
          "shows_key": "914",
          "showdate": "06/16/74",
          "venue": "Des Moines State Fair Grandstand",
          "city": "Des Moines",
          "state": "IA",
          "set1": [
            "Bertha",
            "Mexicali Blues",
            "Row Jimmy",
            "Beat It On Down The Line",
            "Scarlet Begonias",
            "Black Throated Wind",
            "Sugaree",
            "El Paso",
            "It Must Have Been The Roses",
            "Jack Straw",
            "China Cat Sunflower> I Know You Rider",
            "Around & Around"
          ],
          "set2": [
            "Bertha",
            "Mexicali Blues",
            "Row Jimmy",
            "Beat It On Down The Line",
            "Scarlet Begonias",
            "Black Throated Wind",
            "Sugaree",
            "El Paso",
            "It Must Have Been The Roses",
            "Jack Straw",
            "China Cat Sunflower> I Know You Rider",
            "Around & Around"
          ],
          "set3": [
            "Bertha",
            "Mexicali Blues",
            "Row Jimmy",
            "Beat It On Down The Line",
            "Scarlet Begonias",
            "Black Throated Wind",
            "Sugaree",
            "El Paso",
            "It Must Have Been The Roses",
            "Jack Straw",
            "China Cat Sunflower> I Know You Rider",
            "Around & Around"
          ],
          "comment": "Setlist order not 100% certain. The list here is given in the order of a ~1999-circulated SBD.",
          "lastupdate": "2001-07-03 00:00:00",
          "showyear": "1974",
          "showsuserid": "hamilton"
        },
        "key_16": {
          "name": "Grateful Dead",
          "artist_key": "2",
          "shows_key": "915",
          "showdate": "06/18/74",
          "venue": "Freedom Hall",
          "city": "Louisville",
          "state": "KY",
          "set1": [
            "Soundcheck:\n\nThey Love Each Other",
            "U.S. Blues\n\nSet 1:\n\nPromised Land",
            "It Must Have Been The Roses",
            "Black Throated Wind",
            "Ramble On Rose",
            "Beat It On Down The Line",
            "Loser",
            "Mexicali Blues",
            "Eyes Of The World &gt; China Doll",
            "Around And Around"
          ],
          "set2": [
            "Soundcheck:\n\nThey Love Each Other",
            "U.S. Blues\n\nSet 1:\n\nPromised Land",
            "It Must Have Been The Roses",
            "Black Throated Wind",
            "Ramble On Rose",
            "Beat It On Down The Line",
            "Loser",
            "Mexicali Blues",
            "Eyes Of The World &gt; China Doll",
            "Around And Around"
          ],
          "set3": "",
          "comment": "",
          "lastupdate": "2009-02-13 15:06:19",
          "showyear": "1974",
          "showsuserid": "Puffmon2"
        },
        "key_17": {
          "name": "Grateful Dead",
          "artist_key": "2",
          "shows_key": "916",
          "showdate": "06/20/74",
          "venue": "The Omni",
          "city": "Atlanta",
          "state": "GA",
          "set1": [
            "U.S. Blues",
            "Beat It On Down The Line",
            "Brown Eyed Women",
            "Mexicali Blues",
            "It Must Have Been The Roses",
            "Jack Straw",
            "Me & My Uncle",
            "To Lay Me Down",
            "El Paso",
            "China Cat Sunflower-> I Know You Rider",
            "Around & Around"
          ],
          "set2": [
            "U.S. Blues",
            "Beat It On Down The Line",
            "Brown Eyed Women",
            "Mexicali Blues",
            "It Must Have Been The Roses",
            "Jack Straw",
            "Me & My Uncle",
            "To Lay Me Down",
            "El Paso",
            "China Cat Sunflower-> I Know You Rider",
            "Around & Around"
          ],
          "set3": "",
          "comment": "* = First time played.",
          "lastupdate": "2012-09-25 08:55:07",
          "showyear": "1974",
          "showsuserid": "windmail"
        },
        "key_18": {
          "name": "Grateful Dead",
          "artist_key": "2",
          "shows_key": "917",
          "showdate": "06/22/74",
          "venue": "Jai-Alai Fronton",
          "city": "Miami",
          "state": "FL",
          "set1": [
            "Promised Land",
            "Bertha-> Greatest Story Ever Told",
            "Deal",
            "Me And Bobby McGee",
            "Scarlet Begonias",
            "Jack Straw",
            "Loose Lucy",
            "Mexicali Blues",
            "Sugaree",
            "The Race is On",
            "It Must Have Been The Roses",
            "Playin' In The Band"
          ],
          "set2": [
            "Promised Land",
            "Bertha-> Greatest Story Ever Told",
            "Deal",
            "Me And Bobby McGee",
            "Scarlet Begonias",
            "Jack Straw",
            "Loose Lucy",
            "Mexicali Blues",
            "Sugaree",
            "The Race is On",
            "It Must Have Been The Roses",
            "Playin' In The Band"
          ],
          "set3": "",
          "comment": "",
          "lastupdate": "1996-01-07 00:00:00",
          "showyear": "1974",
          "showsuserid": "system"
        },
        "key_19": {
          "name": "Grateful Dead",
          "artist_key": "2",
          "shows_key": "918",
          "showdate": "06/23/74",
          "venue": "Jai-Alai Fronton",
          "city": "Miami",
          "state": "FL",
          "set1": [
            "Ramble On Rose",
            "Black Throated Wind",
            "Mississippi Half Step",
            "Beat It On Down The Line",
            "Row Jimmy",
            "Jack Straw",
            "Let It Rock",
            "Cumberland Blues",
            "El Paso",
            "To Lay Me Down",
            "Weather Report Suite Prelude-> Weather Report Suite Part 1-> Let It Grow-> China Doll"
          ],
          "set2": [
            "Ramble On Rose",
            "Black Throated Wind",
            "Mississippi Half Step",
            "Beat It On Down The Line",
            "Row Jimmy",
            "Jack Straw",
            "Let It Rock",
            "Cumberland Blues",
            "El Paso",
            "To Lay Me Down",
            "Weather Report Suite Prelude-> Weather Report Suite Part 1-> Let It Grow-> China Doll"
          ],
          "set3": "",
          "comment": "",
          "lastupdate": "1996-01-07 00:00:00",
          "showyear": "1974",
          "showsuserid": "system"
        },
        "key_20": {
          "name": "Grateful Dead",
          "artist_key": "2",
          "shows_key": "919",
          "showdate": "06/26/74",
          "venue": "Providence Civic Center",
          "city": "Providence",
          "state": "RI",
          "set1": [
            "Big River",
            "Brown Eyed Women",
            "Beat It On Down The Line",
            "Scarlet Begonias",
            "Black Throated Wind",
            "Row Jimmy",
            "Mexicali Blues",
            "Deal",
            "The Race is On",
            "Mississippi Half Step",
            "El Paso",
            "Ship of Fools",
            "Weather Report Suite Prelude-> Weather Report Suite Part 1-> Let It Grow-> It Must"
          ],
          "set2": [
            "Big River",
            "Brown Eyed Women",
            "Beat It On Down The Line",
            "Scarlet Begonias",
            "Black Throated Wind",
            "Row Jimmy",
            "Mexicali Blues",
            "Deal",
            "The Race is On",
            "Mississippi Half Step",
            "El Paso",
            "Ship of Fools",
            "Weather Report Suite Prelude-> Weather Report Suite Part 1-> Let It Grow-> It Must"
          ],
          "set3": "",
          "comment": "",
          "lastupdate": "1996-01-07 00:00:00",
          "showyear": "1974",
          "showsuserid": "system"
        },
        "key_21": {
          "name": "Grateful Dead",
          "artist_key": "2",
          "shows_key": "920",
          "showdate": "06/28/74",
          "venue": "Boston Garden",
          "city": "Boston",
          "state": "MA",
          "set1": [
            "Mississippi Half Step-> It Must Have Been The Roses-> Jack Straw",
            "Beat It On Down The Line",
            "Deal",
            "Mexicali Blues",
            "Tennessee Jed",
            "Me And Bobby McGee",
            "Loose Lucy",
            "El Paso",
            "Sugaree",
            "Around & Around"
          ],
          "set2": [
            "Mississippi Half Step-> It Must Have Been The Roses-> Jack Straw",
            "Beat It On Down The Line",
            "Deal",
            "Mexicali Blues",
            "Tennessee Jed",
            "Me And Bobby McGee",
            "Loose Lucy",
            "El Paso",
            "Sugaree",
            "Around & Around"
          ],
          "set3": "",
          "comment": "*Phil & Ned Between sets. This date is featured on <a href= \"http://mars.dead.net\">Dick's Picks 12</a>.",
          "lastupdate": "2001-02-05 00:00:00",
          "showyear": "1974",
          "showsuserid": "system"
        },
        "key_22": {
          "name": "Grateful Dead",
          "artist_key": "2",
          "shows_key": "921",
          "showdate": "06/30/74",
          "venue": "Springfield Civic Center",
          "city": "Springfield",
          "state": "MA",
          "set1": [
            "Don't Ease Me In",
            "Black Throated Wind",
            "Peggy-O",
            "Jack Straw",
            "Loser",
            "Greatest Story Ever Told",
            "Cumberland Blues",
            "Dire Wolf",
            "Playin' In The Band &gt; Uncle John's Band &gt; Playin' In The Band"
          ],
          "set2": [
            "Don't Ease Me In",
            "Black Throated Wind",
            "Peggy-O",
            "Jack Straw",
            "Loser",
            "Greatest Story Ever Told",
            "Cumberland Blues",
            "Dire Wolf",
            "Playin' In The Band &gt; Uncle John's Band &gt; Playin' In The Band"
          ],
          "set3": "",
          "comment": "",
          "lastupdate": "2009-02-18 00:44:18",
          "showyear": "1974",
          "showsuserid": "nugs420247"
        },
        "key_23": {
          "name": "Grateful Dead",
          "artist_key": "2",
          "shows_key": "922",
          "showdate": "07/19/74",
          "venue": "Selland Arena",
          "city": "Fresno",
          "state": "CA",
          "set1": [
            "Bertha",
            "Mexicali Blues",
            "Deal",
            "Beat It On Down The Line",
            "Row Jimmy",
            "Me And Bobby McGee",
            "Scarlet Begonias",
            "El Paso",
            "Tennessee Jed",
            "Playin' In The Band"
          ],
          "set2": [
            "Bertha",
            "Mexicali Blues",
            "Deal",
            "Beat It On Down The Line",
            "Row Jimmy",
            "Me And Bobby McGee",
            "Scarlet Begonias",
            "El Paso",
            "Tennessee Jed",
            "Playin' In The Band"
          ],
          "set3": "",
          "comment": "*Phil & Ned Between sets.**Without Phil",
          "lastupdate": "1996-01-07 00:00:00",
          "showyear": "1974",
          "showsuserid": "system"
        },
        "key_24": {
          "name": "Grateful Dead",
          "artist_key": "2",
          "shows_key": "923",
          "showdate": "07/21/74",
          "venue": "Hollywood Bowl",
          "city": "Los Angeles",
          "state": "CA",
          "set1": [
            "Promised Land",
            "Tennessee Jed",
            "Me & My Uncle",
            "Sugaree",
            "Jack Straw",
            "Mississippi Half Step-> It Must Have Been The Roses",
            "El Paso",
            "Scarlet Begonias",
            "Around & Around"
          ],
          "set2": [
            "Promised Land",
            "Tennessee Jed",
            "Me & My Uncle",
            "Sugaree",
            "Jack Straw",
            "Mississippi Half Step-> It Must Have Been The Roses",
            "El Paso",
            "Scarlet Begonias",
            "Around & Around"
          ],
          "set3": "",
          "comment": "*Phi & Ned Between sets Commander Cody, Maria Muldar & John Kahn Opened",
          "lastupdate": "1996-01-07 00:00:00",
          "showyear": "1974",
          "showsuserid": "system"
        },
        "key_25": {
          "name": "Grateful Dead",
          "artist_key": "2",
          "shows_key": "924",
          "showdate": "07/25/74",
          "venue": "International Amphitheater",
          "city": "Chicago",
          "state": "IL",
          "set1": [
            "Me & My Uncle",
            "Loose Lucy",
            "Black Throated Wind",
            "Loser",
            "Beat It On Down The Line",
            "Sugaree",
            "Mexicali Blues",
            "Brown Eyed Women",
            "El Paso",
            "Row Jimmy",
            "Weather Report Suite Prelude-> Weather Report Suite Part 1-> Let It Grow-> Around & Around"
          ],
          "set2": [
            "Me & My Uncle",
            "Loose Lucy",
            "Black Throated Wind",
            "Loser",
            "Beat It On Down The Line",
            "Sugaree",
            "Mexicali Blues",
            "Brown Eyed Women",
            "El Paso",
            "Row Jimmy",
            "Weather Report Suite Prelude-> Weather Report Suite Part 1-> Let It Grow-> Around & Around"
          ],
          "set3": "",
          "comment": "*Phil & Ned Between sets.",
          "lastupdate": "2001-06-07 00:00:00",
          "showyear": "1974",
          "showsuserid": "hamilton"
        },
        "key_26": {
          "name": "Grateful Dead",
          "artist_key": "2",
          "shows_key": "925",
          "showdate": "07/27/74",
          "venue": "Civic Center",
          "city": "Roanoke",
          "state": "VA",
          "set1": [
            "Bertha\nMexicali Blues\nRow Jimmy\nJack Straw\nMississippi Half-Step Uptown Toodleoo &gt;\nIt Must Have Been The Roses\nMe And Bobby McGee\nTennessee Jed\nPlayin' In The Band"
          ],
          "set2": [
            "Bertha\nMexicali Blues\nRow Jimmy\nJack Straw\nMississippi Half-Step Uptown Toodleoo &gt;\nIt Must Have Been The Roses\nMe And Bobby McGee\nTennessee Jed\nPlayin' In The Band"
          ],
          "set3": "",
          "comment": "",
          "lastupdate": "2012-02-06 08:56:31",
          "showyear": "1974",
          "showsuserid": "vatec80"
        },
        "key_27": {
          "name": "Grateful Dead",
          "artist_key": "2",
          "shows_key": "926",
          "showdate": "07/29/74",
          "venue": "Capital Centre",
          "city": "Landover",
          "state": "MD",
          "set1": [
            "Promised Land",
            "Sugaree",
            "Black Throated Wind",
            "It Must Have Been The Roses",
            "Cumberland Blues",
            "Scarlet Begonias",
            "Jack Straw",
            "Deal",
            "El Paso",
            "To Lay Me Down",
            "Weather Report Suite Prelude-> Weather Report Suite Part 1-> Let It Grow"
          ],
          "set2": [
            "Promised Land",
            "Sugaree",
            "Black Throated Wind",
            "It Must Have Been The Roses",
            "Cumberland Blues",
            "Scarlet Begonias",
            "Jack Straw",
            "Deal",
            "El Paso",
            "To Lay Me Down",
            "Weather Report Suite Prelude-> Weather Report Suite Part 1-> Let It Grow"
          ],
          "set3": "",
          "comment": "",
          "lastupdate": "1996-01-07 00:00:00",
          "showyear": "1974",
          "showsuserid": "Wharfrat73"
        },
        "key_28": {
          "name": "Grateful Dead",
          "artist_key": "2",
          "shows_key": "927",
          "showdate": "07/31/74",
          "venue": "Dillon Stadium",
          "city": "Hartford",
          "state": "CT",
          "set1": [
            "Scarlet Begonias",
            "Me And My Uncle",
            "Brown Eyed Women",
            "Beat It On Down The Line",
            "Mississippi Half-Step Uptown Toodeloo -> It Must Have Been The Roses",
            "Mexicali Blues",
            "Row Jimmy",
            "Jack Straw",
            "China Cat Sunflower -> I Know You Rider",
            "Around And Around"
          ],
          "set2": [
            "Scarlet Begonias",
            "Me And My Uncle",
            "Brown Eyed Women",
            "Beat It On Down The Line",
            "Mississippi Half-Step Uptown Toodeloo -> It Must Have Been The Roses",
            "Mexicali Blues",
            "Row Jimmy",
            "Jack Straw",
            "China Cat Sunflower -> I Know You Rider",
            "Around And Around"
          ],
          "set3": [
            "Scarlet Begonias",
            "Me And My Uncle",
            "Brown Eyed Women",
            "Beat It On Down The Line",
            "Mississippi Half-Step Uptown Toodeloo -> It Must Have Been The Roses",
            "Mexicali Blues",
            "Row Jimmy",
            "Jack Straw",
            "China Cat Sunflower -> I Know You Rider",
            "Around And Around"
          ],
          "comment": "Phil & Ned between sets 2 & 3",
          "lastupdate": "1996-01-07 00:00:00",
          "showyear": "1974",
          "showsuserid": "stark1"
        },
        "key_29": {
          "name": "Grateful Dead",
          "artist_key": "2",
          "shows_key": "928",
          "showdate": "08/04/74",
          "venue": "Philadelphia Civic Arena",
          "city": "Philadelphia",
          "state": "PA",
          "set1": [
            "Bertha",
            "Mexicali Blues",
            "Scarlet Begonias",
            "Black Throated Wind",
            "Deal",
            "Beat It On Down The Line",
            "Peggy-O",
            "Jack Straw",
            "Loser",
            "El Paso",
            "Row Jimmy",
            "Playin' In The Band"
          ],
          "set2": [
            "Bertha",
            "Mexicali Blues",
            "Scarlet Begonias",
            "Black Throated Wind",
            "Deal",
            "Beat It On Down The Line",
            "Peggy-O",
            "Jack Straw",
            "Loser",
            "El Paso",
            "Row Jimmy",
            "Playin' In The Band"
          ],
          "set3": "",
          "comment": "*Phil & Ned Between sets.",
          "lastupdate": "1996-01-07 00:00:00",
          "showyear": "1974",
          "showsuserid": "system"
        },
        "key_30": {
          "name": "Grateful Dead",
          "artist_key": "2",
          "shows_key": "929",
          "showdate": "08/05/74",
          "venue": "Philadelphia Civic Arena",
          "city": "Philadelphia",
          "state": "PA",
          "set1": [
            "Promised Land",
            "Brown Eyed Women",
            "Beat It On Down The Line",
            "Dire Wolf",
            "Me And Bobby McGee",
            "Tennessee Jed",
            "Jack Straw",
            "Deal",
            "El Paso",
            "China Cat Sunflower-> I Know You Rider",
            "Around & Around"
          ],
          "set2": [
            "Promised Land",
            "Brown Eyed Women",
            "Beat It On Down The Line",
            "Dire Wolf",
            "Me And Bobby McGee",
            "Tennessee Jed",
            "Jack Straw",
            "Deal",
            "El Paso",
            "China Cat Sunflower-> I Know You Rider",
            "Around & Around"
          ],
          "set3": "",
          "comment": "*Phil & Ned Between sets.",
          "lastupdate": "1996-01-07 00:00:00",
          "showyear": "1974",
          "showsuserid": "wiedmann"
        },
        "key_31": {
          "name": "Grateful Dead",
          "artist_key": "2",
          "shows_key": "930",
          "showdate": "08/06/74",
          "venue": "Roosevelt Stadium",
          "city": "Jersey City",
          "state": "NJ",
          "set1": [
            "Bertha",
            "Mexicali Blues",
            "Don't Ease Me In",
            "Beat It On Down The Line",
            "Sugaree",
            "Jack Straw",
            "Eyes Of The World",
            "Promised Land",
            "Deal",
            "Playin' In The Band-> Scarlet Begonias-> Playin' In The Band"
          ],
          "set2": [
            "Bertha",
            "Mexicali Blues",
            "Don't Ease Me In",
            "Beat It On Down The Line",
            "Sugaree",
            "Jack Straw",
            "Eyes Of The World",
            "Promised Land",
            "Deal",
            "Playin' In The Band-> Scarlet Begonias-> Playin' In The Band"
          ],
          "set3": "",
          "comment": "*Phil & Ned Between sets.",
          "lastupdate": "1996-01-07 00:00:00",
          "showyear": "1974",
          "showsuserid": "system"
        },
        "key_32": {
          "name": "Grateful Dead",
          "artist_key": "2",
          "shows_key": "931",
          "showdate": "09/09/74",
          "venue": "Alexandra Palace",
          "city": "London",
          "state": "England",
          "set1": [
            "Bertha",
            "Promised Land",
            "It Must Have Been The Roses",
            "Jack Straw",
            "Scarlet Begonias",
            "Mexicali Blues",
            "Row Jimmy",
            "Playin' In The Band"
          ],
          "set2": [
            "Bertha",
            "Promised Land",
            "It Must Have Been The Roses",
            "Jack Straw",
            "Scarlet Begonias",
            "Mexicali Blues",
            "Row Jimmy",
            "Playin' In The Band"
          ],
          "set3": "",
          "comment": "*Second Encore.  This date is featured on <a href= \"http://mars.dead.net\">Dick's Picks 7</a>. (soundcheck = Jack Straw?)",
          "lastupdate": "2003-03-11 00:00:00",
          "showyear": "1974",
          "showsuserid": "system"
        },
        "key_33": {
          "name": "Grateful Dead",
          "artist_key": "2",
          "shows_key": "932",
          "showdate": "09/10/74",
          "venue": "Alexandra Palace",
          "city": "London",
          "state": "England",
          "set1": [
            "Around & Around",
            "Mississippi Half Step",
            "Beat It On Down The Line",
            "Peggy-O",
            "Tennessee Jed",
            "Black Throated Wind",
            "China Cat Sunflower-> I Know You Rider",
            "Loser",
            "Black Peter",
            "Weather Report Suite Prelude-> Weather Report Suite Part 1-> Let It Grow-> Stella Blue"
          ],
          "set2": [
            "Around & Around",
            "Mississippi Half Step",
            "Beat It On Down The Line",
            "Peggy-O",
            "Tennessee Jed",
            "Black Throated Wind",
            "China Cat Sunflower-> I Know You Rider",
            "Loser",
            "Black Peter",
            "Weather Report Suite Prelude-> Weather Report Suite Part 1-> Let It Grow-> Stella Blue"
          ],
          "set3": "",
          "comment": "*Phil & Ned Between sets.  This date is featured on <a href= \"http://mars.dead.net\">Dick's Picks 7</a>.",
          "lastupdate": "2004-09-06 00:00:00",
          "showyear": "1974",
          "showsuserid": "system"
        },
        "key_34": {
          "name": "Grateful Dead",
          "artist_key": "2",
          "shows_key": "65352",
          "showdate": "09/11/74",
          "venue": "Alexandra Palace",
          "city": "London",
          "state": "England",
          "set1": [
            "Scarlet Begonias",
            "Mexicali Blues",
            "Brown Eyed Women",
            "Beat It On Down The Line",
            "Sugaree",
            "Jack Straw",
            "Row Jimmy",
            "Me And Bobby McGee",
            "Tennessee Jed",
            "Big River",
            "It Must Have Been The Roses",
            "Playin' In The Band"
          ],
          "set2": [
            "Scarlet Begonias",
            "Mexicali Blues",
            "Brown Eyed Women",
            "Beat It On Down The Line",
            "Sugaree",
            "Jack Straw",
            "Row Jimmy",
            "Me And Bobby McGee",
            "Tennessee Jed",
            "Big River",
            "It Must Have Been The Roses",
            "Playin' In The Band"
          ],
          "set3": "",
          "comment": "This date is featured on <a href= \"http://mars.dead.net\">Dick's Picks 7</a>.",
          "lastupdate": "2004-09-06 00:00:00",
          "showyear": "1974",
          "showsuserid": "stark1"
        },
        "key_35": {
          "name": "Grateful Dead",
          "artist_key": "2",
          "shows_key": "934",
          "showdate": "09/14/74",
          "venue": "Olympia Halle",
          "city": "Munich",
          "state": "Germany",
          "set1": [
            "Bertha",
            "Me & My Uncle",
            "Deal",
            "Jack Straw",
            "Scarlet Begonias",
            "Promised Land",
            "Loser",
            "El Paso",
            "Row Jimmy",
            "Weather Report Suite Prelude-> Weather Report Suite Part 1-> Let It Grow",
            "Tennessee Jed",
            "Around & Around"
          ],
          "set2": [
            "Bertha",
            "Me & My Uncle",
            "Deal",
            "Jack Straw",
            "Scarlet Begonias",
            "Promised Land",
            "Loser",
            "El Paso",
            "Row Jimmy",
            "Weather Report Suite Prelude-> Weather Report Suite Part 1-> Let It Grow",
            "Tennessee Jed",
            "Around & Around"
          ],
          "set3": "",
          "comment": "*Phil & Ned Between sets.",
          "lastupdate": "2004-09-06 00:00:00",
          "showyear": "1974",
          "showsuserid": "system"
        },
        "key_36": {
          "name": "Grateful Dead",
          "artist_key": "2",
          "shows_key": "935",
          "showdate": "09/18/74",
          "venue": "Parc des Expositions",
          "city": "Dijon",
          "state": "France",
          "set1": [
            "Uncle John's Band",
            "Jack Straw",
            "Friend Of The Devil",
            "Black Throated Wind",
            "Scarlet Begonias",
            "Mexicali Blues",
            "Row Jimmy",
            "Beat It On Down The Line",
            "Deal",
            "The Race is On",
            "To Lay Me Down",
            "Playin' In The Band"
          ],
          "set2": [
            "Uncle John's Band",
            "Jack Straw",
            "Friend Of The Devil",
            "Black Throated Wind",
            "Scarlet Begonias",
            "Mexicali Blues",
            "Row Jimmy",
            "Beat It On Down The Line",
            "Deal",
            "The Race is On",
            "To Lay Me Down",
            "Playin' In The Band"
          ],
          "set3": "",
          "comment": "*Phil & Ned Between sets.",
          "lastupdate": "2001-01-24 00:00:00",
          "showyear": "1974",
          "showsuserid": "hamilton"
        },
        "key_37": {
          "name": "Grateful Dead",
          "artist_key": "2",
          "shows_key": "936",
          "showdate": "09/20/74",
          "venue": "Palais Des Sports",
          "city": "Paris",
          "state": "France",
          "set1": [
            "Cumberland Blues",
            "Jack Straw",
            "It Must Have Been The Roses",
            "Beat It On Down The Line",
            "Scarlet Begonias",
            "Black Throated Wind",
            "Friend Of The Devil",
            "El Paso",
            "Row Jimmy",
            "Weather Report Suite Prelude-> Weather Report Suite Part 1-> Let It Grow-> Stella Blue",
            "Around & Around"
          ],
          "set2": [
            "Cumberland Blues",
            "Jack Straw",
            "It Must Have Been The Roses",
            "Beat It On Down The Line",
            "Scarlet Begonias",
            "Black Throated Wind",
            "Friend Of The Devil",
            "El Paso",
            "Row Jimmy",
            "Weather Report Suite Prelude-> Weather Report Suite Part 1-> Let It Grow-> Stella Blue",
            "Around & Around"
          ],
          "set3": "",
          "comment": "",
          "lastupdate": "2004-09-06 00:00:00",
          "showyear": "1974",
          "showsuserid": "system"
        },
        "key_38": {
          "name": "Grateful Dead",
          "artist_key": "2",
          "shows_key": "937",
          "showdate": "09/21/74",
          "venue": "Palais Des Sports",
          "city": "Paris",
          "state": "France",
          "set1": [
            "Bertha",
            "Mexicali Blues",
            "Sugaree",
            "Promised Land",
            "Peggy-O",
            "Me & My Uncle",
            "Deal",
            "The Race Is On",
            "Loose Lucy",
            "El Paso",
            "Eyes Of The World-&gt; China Doll"
          ],
          "set2": [
            "Bertha",
            "Mexicali Blues",
            "Sugaree",
            "Promised Land",
            "Peggy-O",
            "Me & My Uncle",
            "Deal",
            "The Race Is On",
            "Loose Lucy",
            "El Paso",
            "Eyes Of The World-&gt; China Doll"
          ],
          "set3": [
            "Bertha",
            "Mexicali Blues",
            "Sugaree",
            "Promised Land",
            "Peggy-O",
            "Me & My Uncle",
            "Deal",
            "The Race Is On",
            "Loose Lucy",
            "El Paso",
            "Eyes Of The World-&gt; China Doll"
          ],
          "comment": "Third Set with Ned Lagin",
          "lastupdate": "2006-06-02 10:24:14",
          "showyear": "1974",
          "showsuserid": "m z"
        },
        "key_39": {
          "name": "Grateful Dead",
          "artist_key": "2",
          "shows_key": "240371",
          "showdate": "09/??/74",
          "venue": "Alexandra Palace (Dick's Picks 7)",
          "city": "London",
          "state": "England",
          "set1": [
            "Scarlet Begonias\r\nMexicali Blues\r\nRow Jimmy\r\nBlack-Throated Wind\r\nMississippi Half-Step Uptown Toodeloo\r\nBeat It On Down The Line\r\nTennessee Jed\r\nPlaying In The Band"
          ],
          "set2": [
            "Scarlet Begonias\r\nMexicali Blues\r\nRow Jimmy\r\nBlack-Throated Wind\r\nMississippi Half-Step Uptown Toodeloo\r\nBeat It On Down The Line\r\nTennessee Jed\r\nPlaying In The Band"
          ],
          "set3": [
            "Scarlet Begonias\r\nMexicali Blues\r\nRow Jimmy\r\nBlack-Throated Wind\r\nMississippi Half-Step Uptown Toodeloo\r\nBeat It On Down The Line\r\nTennessee Jed\r\nPlaying In The Band"
          ],
          "comment": "Dicks's Picks Volume Seven.\r\nSets = CD's.",
          "lastupdate": "2007-03-29 09:54:59",
          "showyear": "1974",
          "showsuserid": "system"
        },
        "key_40": {
          "name": "Grateful Dead",
          "artist_key": "2",
          "shows_key": "241224",
          "showdate": "09/??/74",
          "venue": "Alexandra Palace",
          "city": "London",
          "state": "England",
          "set1": "",
          "set2": "",
          "set3": "",
          "comment": "",
          "lastupdate": "2005-01-08 08:16:32",
          "showyear": "1974",
          "showsuserid": "douglaswoody37"
        },
        "key_41": {
          "name": "Grateful Dead",
          "artist_key": "2",
          "shows_key": "938",
          "showdate": "10/16/74",
          "venue": "Winterland Arena",
          "city": "San Francisco",
          "state": "CA",
          "set1": [
            "Bertha",
            "Jack Straw",
            "Deal",
            "Mexicali Blues",
            "It Must Have Been The Roses",
            "Beat It On Down The Line",
            "Scarlet Begonias",
            "Me And Bobby McGee",
            "Tennessee Jed",
            "Cumberland Blues",
            "Row Jimmy",
            "Playing In The Band"
          ],
          "set2": [
            "Bertha",
            "Jack Straw",
            "Deal",
            "Mexicali Blues",
            "It Must Have Been The Roses",
            "Beat It On Down The Line",
            "Scarlet Begonias",
            "Me And Bobby McGee",
            "Tennessee Jed",
            "Cumberland Blues",
            "Row Jimmy",
            "Playing In The Band"
          ],
          "set3": "",
          "comment": "",
          "lastupdate": "1996-01-07 00:00:00",
          "showyear": "1974",
          "showsuserid": "stark1"
        },
        "key_42": {
          "name": "Grateful Dead",
          "artist_key": "2",
          "shows_key": "939",
          "showdate": "10/17/74",
          "venue": "Winterland Arena",
          "city": "San Francisco",
          "state": "CA",
          "set1": [
            "Promised Land",
            "Mississippi Half Step",
            "Black Throated Wind",
            "Friend Of The Devil",
            "Jack Straw",
            "Loser",
            "El Paso",
            "China Cat Sunflower-> I Know You Rider",
            "Me & My Uncle",
            "It Must Have Been The Roses",
            "Weather Report Suite Prelude-> Weather Report Suite Part 1-> Let It Grow"
          ],
          "set2": [
            "Promised Land",
            "Mississippi Half Step",
            "Black Throated Wind",
            "Friend Of The Devil",
            "Jack Straw",
            "Loser",
            "El Paso",
            "China Cat Sunflower-> I Know You Rider",
            "Me & My Uncle",
            "It Must Have Been The Roses",
            "Weather Report Suite Prelude-> Weather Report Suite Part 1-> Let It Grow"
          ],
          "set3": "",
          "comment": "*Phil and Ned Between Sets",
          "lastupdate": "1996-01-07 00:00:00",
          "showyear": "1974",
          "showsuserid": "system"
        },
        "key_43": {
          "name": "Grateful Dead",
          "artist_key": "2",
          "shows_key": "940",
          "showdate": "10/18/74",
          "venue": "Winterland Arena",
          "city": "San Francisco",
          "state": "CA",
          "set1": [
            "Around & Around",
            "Sugaree",
            "Beer Barrel Polka Tuning",
            "Mexicali Blues",
            "Peggy-O",
            "Beat It On Down The Line",
            "Brown Eyed Women",
            "Cumberland Blues",
            "El Paso",
            "Tennessee Jed",
            "Jack Straw",
            "Row Jimmy",
            "Weather Report Suite Prelude-> Weather Report Suite Part 1-> Let It Grow"
          ],
          "set2": [
            "Around & Around",
            "Sugaree",
            "Beer Barrel Polka Tuning",
            "Mexicali Blues",
            "Peggy-O",
            "Beat It On Down The Line",
            "Brown Eyed Women",
            "Cumberland Blues",
            "El Paso",
            "Tennessee Jed",
            "Jack Straw",
            "Row Jimmy",
            "Weather Report Suite Prelude-> Weather Report Suite Part 1-> Let It Grow"
          ],
          "set3": [
            "Around & Around",
            "Sugaree",
            "Beer Barrel Polka Tuning",
            "Mexicali Blues",
            "Peggy-O",
            "Beat It On Down The Line",
            "Brown Eyed Women",
            "Cumberland Blues",
            "El Paso",
            "Tennessee Jed",
            "Jack Straw",
            "Row Jimmy",
            "Weather Report Suite Prelude-> Weather Report Suite Part 1-> Let It Grow"
          ],
          "comment": "",
          "lastupdate": "1996-01-07 00:00:00",
          "showyear": "1974",
          "showsuserid": "system"
        },
        "key_44": {
          "name": "Grateful Dead",
          "artist_key": "2",
          "shows_key": "941",
          "showdate": "10/19/74",
          "venue": "Winterland Arena",
          "city": "San Francisco",
          "state": "CA",
          "set1": [
            "Mississippi Half Step",
            "Me & My Uncle",
            "Friend Of The Devil",
            "Beat It On Down The Line",
            "It Must Have Been The Roses",
            "El Paso",
            "Loose Lucy",
            "Black Throated Wind",
            "Scarlet Begonias",
            "To Lay Me Down",
            "Mama Tried",
            "Eyes Of The World-> China Doll",
            "Big River"
          ],
          "set2": [
            "Mississippi Half Step",
            "Me & My Uncle",
            "Friend Of The Devil",
            "Beat It On Down The Line",
            "It Must Have Been The Roses",
            "El Paso",
            "Loose Lucy",
            "Black Throated Wind",
            "Scarlet Begonias",
            "To Lay Me Down",
            "Mama Tried",
            "Eyes Of The World-> China Doll",
            "Big River"
          ],
          "set3": "",
          "comment": "",
          "lastupdate": "1996-01-07 00:00:00",
          "showyear": "1974",
          "showsuserid": "system"
        },
        "key_45": {
          "name": "Grateful Dead",
          "artist_key": "2",
          "shows_key": "942",
          "showdate": "10/20/74",
          "venue": "Winterland Arena",
          "city": "San Francisco",
          "state": "CA",
          "set1": [
            "Cold Rain & Snow",
            "Mama Tried",
            "Deal",
            "Beat It On Down The Line",
            "Loser",
            "Jack Straw",
            "Tennessee Jed",
            "El Paso",
            "Brokedown Palace",
            "China Cat Sunflower-> I Know You Rider",
            "Around & Around"
          ],
          "set2": [
            "Cold Rain & Snow",
            "Mama Tried",
            "Deal",
            "Beat It On Down The Line",
            "Loser",
            "Jack Straw",
            "Tennessee Jed",
            "El Paso",
            "Brokedown Palace",
            "China Cat Sunflower-> I Know You Rider",
            "Around & Around"
          ],
          "set3": [
            "Cold Rain & Snow",
            "Mama Tried",
            "Deal",
            "Beat It On Down The Line",
            "Loser",
            "Jack Straw",
            "Tennessee Jed",
            "El Paso",
            "Brokedown Palace",
            "China Cat Sunflower-> I Know You Rider",
            "Around & Around"
          ],
          "comment": "*with Mickey Hart; Last Wall of Sound show; Phil Lesh and Ned Lagin (\"Seastones\") between sets",
          "lastupdate": "2001-06-19 00:00:00",
          "showyear": "1974",
          "showsuserid": "system"
        },
        "key_46": {
          "name": "Grateful Dead",
          "artist_key": "2",
          "shows_key": "258955",
          "showdate": "10/??/74",
          "venue": "Winterland Arena",
          "city": "San Franciso",
          "state": "CA",
          "set1": [
            "US Blues \r\nOne More Saturday Night\r\nChina Cat Sunflower> \r\nI Know You Rider\r\nEyes of the World> \r\nChina Doll \r\nPlaying In The Band \r\nScarlet Begonias \r\nHe?s Gone> \r\nJam>\r\nWeirdness>\r\nThe Other One>\r\nSpanish Jam>\r\nMind Left Body Jam>\r\nThe Other One>\r\nStella Blue\r\nCasey Jones\r\nUncle John?s Band \r\nBig Railroad Blues \r\nTomorrow Is Forever \r\nSugar Magnolia> \r\nHe?s Gone> \r\nCaution Jam> \r\nDrums> \r\nSpace>\r\nTruckin?>\r\nBlack Peter \r\nSunshine Daydream\r\nWeather Report Suite \r\nJam> \r\nDark Star>\r\nMorning Dew \r\nNot Fade Away> \r\nGoin? Down The Road Feeling Bad>\r\nSoundcheck\r\nPlaying In The Band> \r\nDrums>\r\nNot Fade Away>\r\nDrums>\r\nThe Other One>\r\nWharf Rat>\r\nPlaying In The Band\r\nJohnny B. Goode \r\nMississippi Half Step Uptown Toodeloo> \r\nWe Bid You Goodnight"
          ],
          "set2": "",
          "set3": "",
          "comment": "The Grateful Dead Movie soundtrack. 5 disc set. recorded 10.16-10.20, 1974.",
          "lastupdate": "2006-03-02 20:24:42",
          "showyear": "1974",
          "showsuserid": "rebaman39"
        },
        "key_47": {
          "name": "Grateful Dead",
          "artist_key": "2",
          "shows_key": "319410",
          "showdate": "12/01/74",
          "venue": "Studio",
          "city": "Unknown",
          "state": "Unknown",
          "set1": [
            "Pride Of Cucamonga",
            "Money Money",
            "Unbroken Chain",
            "Unbroken Chain",
            "Unbroken Chain",
            "Scarlet Begonias",
            "Pride of Cucamonga",
            "Ship Of Fools",
            "Money Money",
            "Loose Lucy",
            "Unbroken Chain",
            "Scarlet Begonias",
            "Pride Of Cucamonga",
            "Ship Of Fools",
            "Money Money",
            "Loose Lucy",
            "US Blues"
          ],
          "set2": "",
          "set3": "",
          "comment": "",
          "lastupdate": "2006-05-25 16:59:51",
          "showyear": "1974",
          "showsuserid": "GDead321"
        },
        "key_48": {
          "name": "Grateful Dead",
          "artist_key": "2",
          "shows_key": "294292",
          "showdate": "12/??/74",
          "venue": "Unknown",
          "city": "Unknown",
          "state": "Unknown",
          "set1": "",
          "set2": "",
          "set3": "",
          "comment": "Mars Hotel Sessions",
          "lastupdate": "2006-01-07 02:01:57",
          "showyear": "1974",
          "showsuserid": "sddan"
        },
        "key_49": {
          "name": "Grateful Dead",
          "artist_key": "2",
          "shows_key": "51081",
          "showdate": "??/??/74",
          "venue": "China-Rider Compilation",
          "city": "Various",
          "state": "Various",
          "set1": [
            "2-22 S:RM:P:D:CD",
            "2-24 S:RM:D:CD",
            "3-23 S:RM:D:CD",
            "5-12 S:RM:C:D:C:CD 5-17 S:RM:C:D:CD 5-19 S:RM:C:D:CD 5-25 S:RM:C:D:CD 6-8 AUD:CM:R:D:CD 6-16 S:RM:C:D:CD 6-20 S:RM:C:D:CD"
          ],
          "set2": [
            "2-22 S:RM:P:D:CD",
            "2-24 S:RM:D:CD",
            "3-23 S:RM:D:CD",
            "5-12 S:RM:C:D:C:CD 5-17 S:RM:C:D:CD 5-19 S:RM:C:D:CD 5-25 S:RM:C:D:CD 6-8 AUD:CM:R:D:CD 6-16 S:RM:C:D:CD 6-20 S:RM:C:D:CD"
          ],
          "set3": "",
          "comment": "DSH Show Record Notes: I merged the former xx/xx/74 China-Rider entry to prepare for a shn link, hich needs the ?? format. A former ??/??/74 listing is apparently part of \"Dick's Gift\", Legion of Mary/Jerry Garcia material, and doesn't really belong in the Grateful Dead listing.",
          "lastupdate": "2002-02-16 00:00:00",
          "showyear": "1974",
          "showsuserid": "hamilton"
        },
        "key_50": {
          "name": "Grateful Dead",
          "artist_key": "2",
          "shows_key": "70353",
          "showdate": "??/??/74",
          "venue": "Studio (Mars Hotel Outtakes)",
          "city": "Unknown",
          "state": "CA",
          "set1": [
            "Pride Of Cucamonga [6:40]\r\nMoney Money [5:41]\r\nUnbroken Chain [8:03]\r\nUnbroken Chain [6:19]\r\nUnbroken Chain [6:47]\r\nScarlet Begonias [4:20]\r\nPride Of Cucamonga [4:24]\r\nShip Of Fools [5:00]\r\nMoney Money [4:25]\r\nLoose Lucy [3:14]\r\nUS Blues [4:40]\r\nCrazy Fingers [6:22]"
          ],
          "set2": [
            "Pride Of Cucamonga [6:40]\r\nMoney Money [5:41]\r\nUnbroken Chain [8:03]\r\nUnbroken Chain [6:19]\r\nUnbroken Chain [6:47]\r\nScarlet Begonias [4:20]\r\nPride Of Cucamonga [4:24]\r\nShip Of Fools [5:00]\r\nMoney Money [4:25]\r\nLoose Lucy [3:14]\r\nUS Blues [4:40]\r\nCrazy Fingers [6:22]"
          ],
          "set3": "",
          "comment": "Session 2- All Songs Are Performed Instrumental",
          "lastupdate": "2008-10-02 14:51:16",
          "showyear": "1974",
          "showsuserid": "diana"
        }
      },
      "status": "success"
    }
  }
}